Workbook

Sheet Tracker Field Mapping
A1: Added | B1: SQL MAPPING | C1: Sl No | D1: CTE | F1: Column Name | G1: Description | H1: From System | I1: Front End Field Name | J1: Back End Field Name | K1: Current Status | L1: Comment | M1: Remarks
A2: + | B2: _branch_bu | C2: 1 | D2: pre_calc | F2: BU | G2: value IFS / GDC / UDC / Return | H2: FOCUS | I2: Branch | J2: contact_branch(Shipment Details API) | K2: Available | L2: On COMS user should be able to select Branch while creating shipment.
A3: + | B3: _supplier_name _supplier_code | C3: 2 | D3: pre_calc | F3: Supplier | H3: COMS | I3: Supplier Name | K3: Available | L3: Case 1( PO# line items with Remaining Quantity>0 ) Show the respective Supplier Name of that Line Item. Case 2 (Frieght Order line with Single PO# exists) Show the respective Supplier Name of that shipment. Case 3 (Freight Order line with multiple PO# exists) Show Supplier Name of the PO# which is showing on EKPOREF# column.
A4: + | B4: _po_no_EKPOREF | C4: 3 | D4: pre_calc | F4: EKPOREF# | G4: PO# | H4: COMS | I4: PO # | K4: Available | L4: Case 1( PO# line items with Remaining Quantity>0 ) Show the respective PO# of that Line Item. Case 2 (Frieght Order line with Single PO# exists) Show the respective PO# of that shipment. Case 3 (Freight Order line with multiple PO# exists) Display any one PO# that has the latest CURRENT_PO_PROMISED_DT among all associated PO line items.
A5: + | B5: _secondary_po | C5: 4 | D5: pre_calc | F5: SECONDARY PO | H5: COMS | I5: Show all other PO# seperated by comma except the PO# showing in the EKPOREF# | K5: Available | L5: Case 1 ( PO# line items with Remaining Quantity>0 ) Empty Case 2 (Freight Order line with Single PO# exists) Empty Case 3 (Freight Order line with multiple PO# exists) Display all other PO# values associated with the Freight Order, separated by commas, excluding the PO# shown in the EKPOREF# column.
A6: + | B6: _po_remarks | C6: 5 | D6: pre_calc | F6: PO REMARKS | H6: COMS | I6: PO Remarks | K6: Available | L6: Case 1(PO# line items with Remaining Quantity>0 or Freight Order line with Single PO# exists ) Show the respective PO Remarks of that PO# Line Item. Case 2 (Freight Order line with multiple PO# exists) Display all the remarks associated with the PO line items included in the Freight Order, separated by a " | " delimiter.
A7: + | B7: _commodity | C7: 6 | D7: pre_calc | F7: COMMODITY | H7: COMS | I7: show all different Freight Order Line Item Description | K7: Available | L7: Case 1 ( PO# line items with Remaining Quantity>0 ) show the corresponding PO line item Description. Case 2 (Freight Order line) Display all distinct PO line item descriptions associated with the Freight Order, separated by the "|" symbol.
A8: + | B8: _iss_ref | C8: 7 | D8: pre_calc | F8: ISS REF | H8: COMS | I8: Show the Freight Order No | K8: Available | L8: Case 1 ( PO# line items with Remaining Quantity>0 ) Empty. Case 2 (Freight Order line) Display the Freight Order Number associated with the corresponding shipment.
A9: + | C9: 8 | D9: pre_calc | F9: MODE | H9: FOCUS | I9: Service | J9: service(Shipment Details API) | K9: Available
A10: + | B10: _routed_by | C10: 9 | D10: pre_calc | F10: ROUTED BY | H10: COMS | I10: Routed By | K10: Available
A11: + | B11: _incoterms _incoterms_fo | C11: 10 | D11: pre_calc | F11: INCOTERMS | H11: FOCUS | I11: Shipping Terms | J11: Case 1 ( Freight Order line but shipment not created) Show the value from Inco Terms form Freight Order enrichment table on COMS Case 2 (Freight Order line but Shipment created) shipping_terms(Shipment Details API) | K11: Available | L11: Case 1 ( Freight Order line but shipment not created) Show the value from Inco Terms form Freight Order enrichment table on COMS Case 2 (Freight Order line but Shipment created) shipping_terms(Shipment Details API)
A12: + | B12: _shipment_serial_iss_job | C12: 11 | D12: pre_calc | F12: ISS JOB# | G12: SHIPMENT# | H12: FOCUS | I12: Shipment Serial No | J12: serial_no(Shipment Details API) | K12: Available | L12: Shipment Serial No for the respective Freight Order No
A13: + | B13: _hbl_hawb | C13: 12 | D13: pre_calc | F13: HB/L/HAWB # | G13: HBL#/HAWB# | H13: FOCUS | I13: HB/L Number/HAWB Number | J13: house_no(Shipment Details API) | K13: Available
A14: + | B14: _mbl_mawb | C14: 13 | D14: pre_calc | F14: MBL/MAWB # | G14: MBL#/MAWB# | H14: FOCUS | I14: MB/L Number/MAWB Number | J14: master_no(Shipment Details API) | K14: Available
A15: + | B15: _container_no | C15: 14 | D15: pre_calc | F15: CONTAINER # | G15: Container# | H15: FOCUS | I15: Container Number | J15: equipment_details.*.equipment_no(Shipment Details API) | K15: Available | L15: Show all Container# against the Shipment seperated by Comma
A16: + | B16: _origin_port_pol | C16: 15 | D16: pre_calc | F16: POL | H16: FOCUS | I16: Origin Port/Airport Code | J16: origin_port(Shipment Details API) | K16: Available
A17: + | B17: _origin_port_name | C17: 16 | D17: pre_calc | F17: PORT NAME | H17: FOCUS | I17: Origin Port/Airport Name | J17: to be taken from AVS | K17: Available
A18: + | B18: _origin_country | C18: 17 | D18: pre_calc | F18: ORG COUNTRY | H18: FOCUS | I18: Origin Port/Airport Country Name | J18: to be taken from AVS | K18: Available
A19: + | B19: _origin_region_org_reg | C19: 18 | D19: pre_calc | F19: ORG REGION | H19: FOCUS | I19: Origin Port/Airport Country Region | J19: to be taken from AVS | K19: Available
A20: + | B20: _destination_port_code_dest _destination_port_name_dest _destination_country_code_dest _destination_country_dest _destination_region_reg | C20: 19 | D20: pre_calc | F20: DEST | H20: FOCUS | I20: Destination Port/Airport Code | J20: Name to be taken from AVS+"("+destination_port(Shipment Details API)+")" | K20: Available | L20: show both port code and name
A21: + | B21: _eqpt_type | C21: 20 | D21: pre_calc | F21: EQPT TYPE | H21: FOCUS | I21: Container Type | J21: equipment(Shipment Details API) | K21: Available | L21: Show the value in the format "Total No of Container" * "Container Type".Each container type should be seperated by "+".Say eg: 2 x 20 ft Standard Dry + 1 x 40 ft Standard Dry
A22: + | B22: _20_ft | C22: 21 | D22: pre_calc | F22: 20' | H22: FOCUS | J22: Total Count of 20 ft equipment_details.*.container_type(Shipment Details API) | K22: Available | L22: Show the total No of Containers of 20 feet container type
A23: + | B23: _40_ft | C23: 22 | D23: pre_calc | F23: 40' | H23: FOCUS | J23: Total Count of 40 ft equipment_details.*.container_type(Shipment Details API) | K23: Available | L23: Show the total No of Containers of 40 feet container type
A24: + | B24: _count_of_cont | C24: 23 | D24: pre_calc | F24: # OF CONT. | H24: FOCUS | I24: Show the total No of Containers | J24: Total Count of equipment_details.*.equipment_no(Shipment Details API) | K24: Available | L24: Show the total No of Containers
A25: + | B25: _teus | C25: 24 | D25: pre_calc | F25: # of TEU's | H25: FOCUS | I25: Show the total no of Teus | J25: Calculate total Teus based on equipment_details array(Shipment Details API) | K25: Available | L25: Show the total no of Teus
A26: + | B26: _carrier | C26: 25 | D26: pre_calc | F26: Carrier | H26: FOCUS | I26: Shipping Line/Air Line | J26: Show same like Carrier value showing in AVS | K26: Available | L26: For the Ocean Import take the value from Shipping Line but for Ocean Export take the value from Carrier.Air jobs it will be always Airline.
A27: + | B27: _pr_appr_date | C27: 26 | D27: pre_calc | F27: PR APPR DATE | H27: COMS | I27: REQ_APP_DT | K27: Available | L27: Case 1 ( PO# line items with Remaining Quantity>0 ) Show the REQ_APP_DT of the respective PO Line item. Case 2 (Freight Order line) Display the REQ_APP_DT of the PO number shown in the EKPOREF# column.
A28: + | B28: _po_appr_date | C28: 27 | D28: pre_calc | F28: PO APPR DATE | H28: COMS | I28: PO_APP_DT | K28: Available | L28: Case 1 ( PO# line items with Remaining Quantity>0 ) Show the PO_APP_DT of the respective PO Line item. Case 2 (Freight Order line) Display the PO_APP_DT of the PO number referenced in the EKPOREF# column
A29: + | B29: _po_creation_date | C29: 28 | D29: pre_calc | F29: PO CREATION DATE | G29: PO Created Date | H29: COMS | I29: PO_DATE | K29: Available | L29: Case 1 ( PO# line items with Remaining Quantity>0 ) Show the PO_DATE of the respective PO Line item. Case 2 (Freight Order line) Display the PO_DATE of the PO# shown in the EKPOREF# column
A30: + | B30: _po_recd_date | C30: 29 | D30: pre_calc | F30: PO RECD DATE | G30: PO Received Date | H30: COMS | I30: PO_APP_DT+2 Days | K30: Calculation | L30: Case 1 ( PO# line items with Remaining Quantity>0 ) Show the PO_APP_DT + 2 Days of the respective PO Line item. Case 2 (Freight Order line) Display the value of PO_APP_DT + 2 days for the PO# shown in the EKPOREF# column
A31: + | B31: _po_need_by_date | C31: 30 | D31: pre_calc | F31: PO NEED BY DATE | G31: Current Promise Date | H31: COMS | I31: CURRENT_PO_PROMISED_DT | K31: Available | L31: Case 1 ( PO# line items with Remaining Quantity>0 ) Show the CURRENT_PO_PROMISED_DT of the respective PO Line item. Case 2 (Freight Order line) Display the latest CURRENT_PO_PROMISED_DT from the PO Line Items associated with the PO# shown in the EKPOREF# column.
A32: + | B32: _crd | C32: 31 | D32: pre_calc | F32: CRD | G32: Cargo Readiness Date | H32: FOCUS | I32: Cargo Ready Date Actual | J32: Cargo Ready Date from focus__shipments table | K32: Available
A33: + | B33: _pickup_date | C33: 32 | D33: pre_calc | F33: Pick Up | H33: FOCUS | I33: Pickup/Stuffing Date | J33: pickup_date(Shipment Details API) | K33: Available
A34: + | B34: _cargo_ho | C34: 33 | D34: pre_calc | F34: Cargo H/O | H34: FOCUS | I34: Pickup/Stuffing Date | J34: pickup_date(Shipment Details API) | K34: Available
A35: + | B35: _etd | C35: 34 | D35: pre_calc | F35: ETD | H35: FOCUS | I35: PTD(Wakeo) | J35: etd_wakeo_date(Shipment Details API) | K35: Available
A36: + | B36: _revised_etd | C36: 35 | D36: pre_calc | F36: REVISED ETD | H36: FOCUS | I36: ETD | J36: etd_date(Shipment Details API) | K36: Available
A37: + | B37: _eta | C37: 36 | D37: pre_calc | F37: ETA | H37: FOCUS | I37: PTA(Wakeo) | J37: eta_wakeo_date(Shipment Details API) | K37: Available
A38: + | B38: _revised_eta | C38: 37 | D38: pre_calc | F38: REVISED ETA | H38: FOCUS | I38: ETA | J38: eta_date(Shipment Details API) | K38: Available
A39: + | B39: _do_exp _do_date | C39: 38 | D39: pre_calc | F39: D/O EXP | H39: FOCUS | I39: D/O Expiry Date | J39: ??? | K39: Not Available | M39: New Field needs to create in FOCUS Production environment by Bendetta as "D/O Expiry Date"
A40: + | B40: _del | C40: 39 | D40: pre_calc | F40: DEL | H40: FOCUS | I40: Delivery Date | J40: delivery_date(Shipment Details API) | K40: Available
A41: + | B41: _status | C41: 40 | D41: pre_calc | F41: STATUS | H41: COMS | K41: Calculation | L41: Case 1 (PO# line items with Remaining Quantity>0 ) Pending = PO is not cancelled and Current Promise Date <= Current Date + 90 Days and Current Promise Date > Current Date Not Due = PO is not cancelled and Current Promise Date > Current Date + 90 Days Due = PO is not cancelled and Current Promise Date <= Current Date Cancelled = if the PO is cancelled in COMS. Case 2 (Freight Order line) On Going = (Freight Order Created and Shipment not created) or (Shipment Created and Shipment is not Cancelled in FOCUS and (Actual Time of Departure is in the future OR not yet entered)) In Transit =Shipment is not Cancelled in FOCUS and Actual Time of Departure is recorded AND Actual Time of Departure <= Current Date AND (Actual Time of Arrival is empty or Actual Time of Arrival>Current Date) Arrived = Shipment is not Cancelled in FOCUS and Actual Time of Arrival is recorded AND Actual Time of Arrival ≤ Current Date AND (Delivery Date is empty or Delivery Date > Current Date) Delivered = Shipment is not Cancelled in FOCUS and Delivery Date is recorded AND Delivery Date ≤ Current Date Cancelled = Freight Order is marked as cancelled in COMS | M41: Case 1 ( PO# line items with Remaining Quantity>0 ) Current Promise Date=CURRENT_PO_PROMISED_DT of the respective PO Line item. Case 2 (Freight Order line) Current Promise Date= latest CURRENT_PO_PROMISED_DT from the PO Line Items associated with the PO# shown in the EKPOREF# column.
A42: + | B42: _delivery_location | C42: 41 | D42: pre_calc | F42: DELIVERY LOCATION | H42: COMS | I42: Delivery Location | J42: Delivery Location from COMS | K42: Available
A43: + | B43: _inner_qty | C43: 42 | D43: pre_calc | F43: INNER QTY | H43: COMS | K43: Available | L43: Case 1 (PO# line items with Remaining Quantity>0 ) • INNER QUANTITY will be Remaining Quantity of that PO line item Case 2 (Freight Order line) • If the Freight Order contains a single PO number, Inner Quantity = Total Used Quantity for the entire Freight Order. • If the Freight Order includes multiple PO numbers, display the quantity in the following format: "PO# - Total Used Quantity of that PO | PO# - Total Used Quantity of that PO | ..." Example: 415007844-144 | 415007844-200 | 415007844-600 | 423005561-520
A44: + | B44: _cbm | C44: 43 | D44: pre_calc | F44: CBM (gross_volume from ship response) | H44: FOCUS | I44: Total Gross Volume from Cargo | J44: gross_volume(Shipment Details API) | K44: Available
A45: + | B45: _gross_weight | C45: 44 | D45: pre_calc | F45: G/W (KGS.) | H45: FOCUS | I45: Total Gross Weight from Cargo | J45: gross_weight(Shipment Details API) | K45: Available
A46: + | B46: _chargeable_weight | C46: 45 | D46: pre_calc | F46: C/W (KGS.) | H46: FOCUS | I46: Total Chargeable Weight from Cargo | J46: chargeable_weight(Shipment Details API) | K46: Available
A47: + | B47: _quantity | C47: 46 | D47: pre_calc | F47: QTY | H47: FOCUS | I47: Total No of Packages from Cargo | J47: package_count(Shipment Details API) | K47: Available
A48: + | B48: _pack_type | C48: 47 | D48: pre_calc | F48: PACK TYPE | H48: FOCUS | I48: Type of Package from Cargo Section | J48: From Array cargo.*.package_type(Shipment Details API) | K48: Available
A49: + | B49: _customs_invoice_aed | C49: 48 | D49: pre_calc | F49: Invoice (AED) | H49: FOCUS | I49: Declaration Value under Customs | J49: ??? | K49: Available | L49: focus_customs -> declaration value (column)
B50: _ship_remarks_updates | C50: 50 | D50: pre_calc | F50: SHIPMENT REMARKS/UPDATES | H50: COMS | I50: Shipment Remarks | K50: Available | L50: New "Shipment Remarks" field needs to be added in COMS shipment page and needs to save in COMS. Take the value from Shipment page in COMS.
A51: + | B51: _pre_alert | C51: 51 | D51: pre_calc | F51: P/A Sent | H51: COMS | I51: Pre Alert Sent Status | K51: Available | L51: Show it as "Yes" if the Pre Alert Sent through COMS else show as "No".
A52: + | B52: _dn | C52: 52 | D52: pre_calc | E52: perf | F52: D/N | H52: FOCUS | I52: Document Label "AGI" attached then show it as "YES", else "No". | J52: Field Label with Value="AGI" from Focus attachments API then show it as "YES", else "No". | K52: Available | L52: We need to add a new Document Label in FOCUS "AGI".Need to discuss with Bendetta (get from attachments -> lable= AGI
A53: + | B53: _ontime_order_placement_perf | C53: 53 | D53: pre_calc | E53: perf | F53: ON TIME ORDER PLACEMENT PERF % | H53: COMS | I53: COMS Tracker to calculate and display the value accordingly | K53: Calculation | L53: If(PO_APP_DT>0) then { if( (PO_APP_DT-REQ_APP_DT)<=5) then {Value=100} else {Value=(1-ABS(PO_APP_DT-REQ_APP_DT)/5})*100 } else {Value=0} | M53: Amended: Case 2 (Freight Order line) REQ_APP_DT = REQ_APP_DT of the PO number shown in the EKPOREF# column. PO_APP_DT= PO_APP_DT of the PO number referenced in the EKPOREF# column • Show the Value sufffixed with symbol " %" | N53: show only for _po_no_ekporef (where one doc is sitting)
A54: + | B54: _supplier_committed_prod_rdy_perf | C54: 54 | D54: pre_calc | E54: perf | F54: Supplier committed product readiness performance % | H54: COMS | I54: COMS Tracker to calculate and display the value accordingly | J54: how to split/add conditions for PO lines and Freight order lines | K54: Calculation | L54: If(PO_APP_DT="" or Cargo Ready Date Actual="") {Value=0 } else if (Cargo Ready Date Actual-PO_APP_DT<=Supplier Lead Time) {Value=100} else if(Cargo Ready Date Actual-PO_APP_DT)>Supplier Lead Time) {Value=(1-ABS(Cargo Ready Date Actual-PO_APP_DT)/Supplier Lead Time})*100 else {Value=""} | M54: Amended: Case 2 (Freight Order line) • PO_APP_DT= PO_APP_DT of the PO number referenced in the EKPOREF# column • Show the Value sufffixed with symbol " %" | N54: show only for _po_no_ekporef (where one doc is sitting) only for FO lines
A55: + | B55: _iss_cont_booking_perf | C55: 55 | D55: calc | E55: perf | F55: ISS container booking performance % | H55: COMS | I55: COMS Tracker to calculate and display the value accordingly | K55: Calculation | L55: If(ETD>0 AND No. of Days ISS Cont. Booking LT>0) { if(ETD-Cargo Ready Date Actual<=7) {Value=100} else {Value=(1-ABS(ETD-Cargo Ready Date Actual)/7})*100 } else {Value=0} | M55: • ETD = PTD(Wakeo) • Cargo Ready Date Actual = CRD • Show the Value sufffixed with symbol " %"
A56: + | B56: _iss_transit_lead_time_perf | C56: 56 | D56: calc | E56: perf | F56: ISS Transit Lead Time Perf % | H56: COMS | I56: COMS Tracker to calculate and display the value accordingly | K56: Calculation | L56: if (DeliveryDate="" || OriginCountryName="" || ETD="" || ETA="") {Value=0 } else if((ETA-ETD) <= OriginCountryLeadTime) {Value=100} else if((ETA-ETD) > OriginCountryLeadTime) {Value=(1-ABS(ETA-ETD) / OriginCountryLeadTime})*100 | M56: • OriginCountryName = Origin Port/Airport Country Name • ETD = PTD(Wakeo) • ETA = PTA(Wakeo) • OriginCountryLeadTime = Lead Time against Corresponding Country in Country Transit Time Master • Show the Value sufffixed with symbol " %"
A57: + | B57: _iss_custom_clear_perf | C57: 57 | D57: calc | E57: perf | F57: ISS custom clearance Perf % | H57: COMS | I57: COMS Tracker to calculate and display the value accordingly | K57: Calculation | L57: if (DeliveryDate="" || ETA="") {Value=0;} else if((DeliveryDate-ETA) <= 3) {Value=100} else if((DeliveryDate-ETA) > 3) {Value=(1-ABS(DeliveryDate-ETA) / 3})*100 | M57: • ETD = PTD(Wakeo) • ETA = PTA(Wakeo) • Show the Value sufffixed with symbol " %"
A58: + | B58: _e2e_total_lead_time_perf | C58: 58 | D58: calc | E58: perf | F58: E2E TOTAL LEAD TIME ACCURACY | H58: COMS | I58: COMS Tracker to calculate and display the value accordingly | K58: Calculation | L58: IF(E2E Total LT>0), {Value=(1-ABS(E2E Total LT-No of Days Total Comm LT)/No of Days Total Comm LT})*100 else {Value=0} | M58: • Show the Value sufffixed with symbol " %"
A59: + | B59: _days_total_comm_perf | C59: 59 | D59: calc | E59: perf | F59: No of Days Total Comm LT (as per contract) | H59: COMS | I59: COMS Tracker to calculate and display the value accordingly | K59: Calculation | L59: if(DeliveryDate="" || STATUS="Cancelled" || OriginCountryName="") {Value=0} else {Value=Supplier Lead Time+OriginCountryLeadTime+7+3+5} | M59: • STATUS=Status Update • Supplier Lead Time = Lead Time against Corresponding supplier in Supplier Lead Time Master • OriginCountryLeadTime = Lead Time against Corresponding Country in Country Transit Time Master
A60: + | B60: _actual_lead | C60: 60 | D60: calc | E60: perf | F60: Actual Lead (PO to Date) | H60: COMS | I60: COMS Tracker to calculate and display the value accordingly | K60: Calculation | L60: if(No of Days Order Placement LT +No. of Days Supplier Production Lead Time +No. of Days Custom Clearance LT +No. of Days ISS Cont. Booking LT +No. of Days Transit LT)>500 {Value=0} else {Value=No of Days Order Placement LT +No. of Days Supplier Production Lead Time +No. of Days Custom Clearance LT +No. of Days ISS Cont. Booking LT}
A61: + | B61: _health_check | C61: 61 | D61: calc | E61: perf | F61: HEALTH CHECK | H61: COMS | I61: COMS Tracker to calculate and display the value accordingly | K61: Calculation | L61: if(No. of Days Supplier Production Lead Time="" || DeliveryDate="" || ETA="" || ETD="" || REQ_APP_DT="" || Actual Lead (PO to Date)="" || No of Days Total Comm LT (as per contract)="") {Value=""} else if(Actual Lead (PO to Date)-No of Days Total Comm LT (as per contract)<=15) {Value="Healthy"} else if(Actual Lead (PO to Date)-No of Days Total Comm LT (as per contract)<=30) {Value="Minor"} else if(Actual Lead (PO to Date)-No of Days Total Comm LT (as per contract)<=45) {Value="Moderate"} else if(Actual Lead (PO to Date)-No of Days Total Comm LT (as per contract)<=60) {Value="Major"} else if(Actual Lead (PO to Date)-No of Days Total Comm LT (as per contract)>60) {Value="Severe"} | M61: Amended: only for FO lines Case 2 (Freight Order line) REQ_APP_DT = REQ_APP_DT of the PO number shown in the EKPOREF# column. | N61: show only for _po_no_ekporef (where one doc is sitting) only for FO lines
B62: _reason_code | C62: 62 | D62: main | E62: perf | F62: REASON CODE | H62: COMS | I62: COMS Tracker to calculate and display the value accordingly | K62: Calculation | L62: if(HEALTH CHECK="" || HEALTH CHECK="Healthy") {Value=""} else if(ON TIME ORDER PLACEMENT PERF %<100%) {Value="PR to PO Delay"} else if(Supplier committed product readiness performance %<100%) {Value="Product Readiness Delay"} else if(ISS container booking performance %<100%) {Value="Booking Delay"} else if(ISS Transit Lead Time Perf %<100%) {Value="Trans Shipment Delay"} else if(ISS custom clearance Perf %<100%) {Value="Custom Clearance Delay"}
A63: + | B63: _days_order_placement_lt | C63: 63 | D63: pre_calc | E63: lead time (LT) | F63: No of Days Order Placement LT | H63: COMS | I63: COMS Tracker to calculate and display the value accordingly | K63: Calculation | L63: if(REQ_APP_DT="" || PO_APP_DT="") {Value=0} else {Value=PO_APP_DT-REQ_APP_DT} | M63: Case 1 ( PO# line items with Remaining Quantity>0 ) REQ_APP_DT= REQ_APP_DT of the respective PO Line item. PO_APP_DT= PO_APP_DT of the respective PO Line item. Case 2 (Freight Order line) REQ_APP_DT = REQ_APP_DT of the PO number shown in the EKPOREF# column. PO_APP_DT= PO_APP_DT of the PO number referenced in the EKPOREF# column
A64: + | B64: _days_supplier_production_lt | C64: 64 | D64: pre_calc | E64: lead time (LT) | F64: No. of Days Supplier Production Lead Time | H64: COMS | I64: COMS Tracker to calculate and display the value accordingly | K64: Calculation | L64: if(DeliveryDate="" || Cargo Ready Date Actual="" || PO_APP_DT="") {Value=0} else {Value=Cargo Ready Date Actual-PO_APP_DT} | M64: Case 1 ( PO# line items with Remaining Quantity>0 ) PO_APP_DT= PO_APP_DT of the respective PO Line item. Case 2 (Freight Order line) PO_APP_DT= PO_APP_DT of the PO number referenced in the EKPOREF# column
A65: + | B65: _days_custom_clearance_lt | C65: 65 | D65: pre_calc | E65: lead time (LT) | F65: No. of Days Custom Clearance LT | H65: COMS | I65: COMS Tracker to calculate and display the value accordingly | K65: Calculation | L65: if(DeliveryDate!="" && ETA!="") {Value=DeliveryDate-ETA) else {Value=0}
A66: + | B66: _days_iss_cont_booking_lt | C66: 66 | D66: pre_calc | E66: lead time (LT) | F66: No. of Days ISS Cont. Booking LT | H66: COMS | I66: COMS Tracker to calculate and display the value accordingly | K66: Calculation | L66: if(ETD>0) {Value=ETD-Cargo Ready Date Actual} else {Value=0} | M66: • ETD = PTD(Wakeo) • Cargo Ready Date Actual = CRD ETA Wakeo -> ETA same for ETD
A67: + | B67: _days_transit_lt | C67: 67 | D67: pre_calc | E67: lead time (LT) | F67: No. of Days Transit LT | H67: COMS | I67: COMS Tracker to calculate and display the value accordingly | K67: Calculation | L67: if(ETA>0) {Value=ETA-ETD} else {Value=0} | M67: • ETD = PTD(Wakeo) • ETA = PTA(Wakeo)
B68: _e2e_total_lt | C68: 68 | D68: pre_calc | E68: lead time (LT) | F68: E2E Total LT | H68: COMS | I68: COMS Tracker to calculate and display the value accordingly | K68: Calculation | L68: if(DeliveryDate="" || REQ_APP_DT="") {Value=0} else {Value=DeliveryDate-REQ_APP_DT} | M68: Case 1 ( PO# line items with Remaining Quantity>0 ) REQ_APP_DT= REQ_APP_DT of the respective PO Line item. Case 2 (Freight Order line) REQ_APP_DT = REQ_APP_DT of the PO number shown in the EKPOREF# column.
B69: _org_chgs_usd | C69: 69 | D69: pre_calc | E69: charges | F69: ORG CHARGES (USD) | H69: FOCUS | I69: Total Expected Revenue of Origin Charges in USD | J69: Value from column B "ORG CHGS (AED)"/3.673 | K69: Available | L69: Value from column "ORG CHGS (AED)"/ use focus__exchange_rates for convertion | M69: Financial part
A70: + | B70: _frt_chrg_usd | C70: 70 | D70: pre_calc | E70: charges | F70: FRT CHGS (USD) | H70: FOCUS | I70: Total Expected Revenue of Ocean Freight & Air Freight Charges in USD | J70: Value from column B "FRT CHGS (AED)"/3.673 | K70: Available | L70: Value from column "FRT CHGS (AED)"/ use focus__exchange_rates for convertion | M70: if shipment serial is empty -> fin values are NULL
A71: + | B71: _dest_chrg_usd | C71: 71 | D71: pre_calc | E71: charges | F71: DEST CHARGES (USD) | H71: FOCUS | I71: Total Expected Revenue of Destination Charges in USD | J71: Value from column B "DEST CHGS (AED)"/3.673 | K71: Available | L71: Value from column "DEST CHGS (AED)"/ use focus__exchange_rates for convertion | M71: take charge type from Charge service mapping file -> use ship serial and service type to get the charge type and then sum up from the table using formula
A72: + | B72: _aux_chrg_aed | C72: 72 | D72: pre_calc | E72: charges | F72: Ancillary Charges (AED) | H72: FOCUS | I72: Total Expected Revenue of Charges from focus__costs_revenues_items table which is configured in COMS Ancillary Charge Master based on Service in AED | J72: Total Expected Revenue from focus__costs_revenues_items table for the Charges which is configured in COMS Ancillary Charge Master based on Service(Air inbound,air outbound,sea inbound etc) in AED | K72: Available | L72: Total Expected Revenue = focus__costs_revenues_items.Selling Rate * focus__costs_revenues_items.Selling Quantity * focus__costs_revenues_items.Selling Local Exchange Rate | M72: mappings (from three files) are for EMIRATES AIRLINE
A73: + | B73: _aux_charge_type | C73: 73 | D73: pre_calc | E73: charges | F73: Ancillary Charge Type | H73: FOCUS | I73: Extra Info for those Charges seperated by "|" which is configured in COMS Ancillary Charge Master based on Service | J73: Extra Info from focus__costs_revenues_items table for the Charges which is configured in COMS Ancillary Charge Master based on Service(Air inbound,air outbound,sea inbound etc) in AED seperated by "|" | K73: Available | L73: Extra Info from focus__costs_revenues_items table for those Charges which is configured in COMS Ancillary Charge Master based on Service seperated by "|" | M73: create tables with mappings in DB + add client ID = 4 (EMIRATES AIRLINE)
A74: + | B74: _org_chrg_aed | C74: 75 | D74: pre_calc | E74: charges | F74: ORG CHGS (AED) | H74: FOCUS | I74: Total Expected Revenue of Origin Charges in AED | J74: Total Expected Revenue of Charges from focus__costs_revenues_items table corresponding to the shipment’s serial number. These charges should be identified based on the Service (air_inbound, air_outbound, sea_inbound, etc.) as configured in the Charge Service Mapping table as category="Origin Charge" | K74: Available | L74: Total Expected Revenue= focus__costs_revenues_items.Selling Rate* focus__costs_revenues_items.Selling Quantity* focus__costs_revenues_items.Selling Local Exchange Rate
A75: + | B75: _frt_chrg_aed | C75: 76 | D75: pre_calc | E75: charges | F75: FRT CHGS (AED) | H75: FOCUS | I75: Total Expected Revenue of Ocean Freight & Air Freight Charges in AED | J75: Total Expected Revenue of Charges from focus__costs_revenues_items table corresponding to the shipment’s serial number. These charges should be identified based on the Service (air_inbound, air_outbound, sea_inbound, etc.) as configured in the Charge Service Mapping table as category="Freight Charge" | K75: Available | L75: Total Expected Revenue= focus__costs_revenues_items.Selling Rate* focus__costs_revenues_items.Selling Quantity* focus__costs_revenues_items.Selling Local Exchange Rate
A76: + | B76: _dest_chrg_aed | C76: 77 | D76: pre_calc | E76: charges | F76: DEST CHGS (AED) | H76: FOCUS | I76: Total Expected Revenue of Destination Charges in AED | J76: Total Expected Revenue of Charges from focus__costs_revenues_items table corresponding to the shipment’s serial number. These charges should be identified based on the Service (air_inbound, air_outbound, sea_inbound, etc.) as configured in the Charge Service Mapping table as category="Destination Charge" | K76: Available | L76: Total Expected Revenue= focus__costs_revenues_items.Selling Rate* focus__costs_revenues_items.Selling Quantity* focus__costs_revenues_items.Selling Local Exchange Rate
A77: + | C77: 78 | D77: pre_calc | E77: charges | F77: P2P VALUE | H77: COMS | I77: COMS Tracker to calculate and display the value accordingly | K77: Calculation | L77: ORG CHGS (AED)+FRT CHGS (AED)+DEST CHGS (AED)
A78: + | B78: _total_charges_aed | C78: 79 | D78: pre_calc | E78: charges | F78: TOTAL CHARGES (AED) | H78: COMS | I78: COMS Tracker to calculate and display the value accordingly | K78: Calculation | L78: Ancillary Charges (AED)+ORG CHGS (AED)+FRT CHGS (AED)+DEST CHGS (AED)
A79: + | B79: _aux_charge_form_no | C79: 74 | F79: Ancilliary Charge Form No | H79: COMS | I79: Ancilliary Charge Form No | K79: Available
B80: _ship_billing_remarks | C80: 80 | D80: pre_calc | E80: pr-req-spo | F80: REQUISITION / BILLING NOTES | H80: COMS | I80: REQUISITION / BILLING NOTES | K80: Available
A81: + | B81: _pr_number | C81: 81 | D81: pre_calc | E81: pr-req-spo | F81: PR # | H81: COMS | I81: PR # | K81: Available | L81: for shipment line only
A82: + | B82: _pr_date | C82: 82 | D82: pre_calc | E82: pr-req-spo | F82: PR DATE | H82: COMS | I82: PR DATE | K82: Available | L82: for shipment line only
A83: + | B83: _req_status | C83: 83 | D83: pre_calc | E83: pr-req-spo | F83: REQ STATUS | H83: COMS | I83: COMS Tracker to calculate and display the value accordingly | K83: Calculation | L83: for shipment line only If(PR #="") {Value="Pending"} else {Value="Logged"}
A84: + | C84: 84 | D84: pre_calc | E84: pr-req-spo | F84: SPO # | H84: FOCUS | I84: SPO No under MBL/MAWB Reference | J84: master_spo_no(Shipment Details API) | K84: Available | L84: for shipment line only
A85: + | C85: 85 | D85: pre_calc | E85: pr-req-spo | F85: PO STATUS | H85: COMS | I85: COMS Tracker to calculate and display the value accordingly | K85: Calculation | L85: for shipment line only If (SPO # ="") {Value="Pending"} else {Value="Received"}
A86: + | C86: 86 | D86: calc | E86: pr-req-spo | F86: SPO /Inv Val(AED) | H86: FOCUS | I86: COMS Tracker to calculate and display the value accordingly | J86: ORG CHGS (AED)+FRT CHGS (AED)+DEST CHGS (AED) | K86: Calculation | L86: ORG CHGS (AED)+FRT CHGS (AED)+DEST CHGS (AED) copy from p2p VALUIE
C87: 87 | F87: Sent to OPS | H87: COMS | I87: Sent to OPS | K87: Not Required
A88: + | C88: 88 | E88: invoice | F88: Invoice # | H88: FOCUS | I88: InvoiceDebit Note No of Normal Charges | J88: Fetch the Serial No from the focus__issued_invoices table where Voided = False, for the charges listed in the focus__costs_revenues_items table corresponding to the shipment’s serial number. These charges should be identified based on the Service (air_inbound, air_outbound, sea_inbound, etc.) as configured in the Charge Service Mapping table as category not equal to "Ancillary Charge", and the multiple focus__issued_invoices.Serial Number should be returned separated by "|" | K88: Available | L88: Fetch the Serial No from the focus__issued_invoices table where Voided = False, for the charges listed in the focus__costs_revenues_items table corresponding to the shipment’s serial number. These charges should be identified based on the Service (air_inbound, air_outbound, sea_inbound, etc.) as configured in the Charge Service Mapping table as category not equal to "Ancillary Charge", and the multiple focus__issued_invoices.Serial Number should be returned separated by "|"
A89: + | C89: 89 | E89: invoice | F89: Billing Status | H89: COMS | I89: COMS Tracker to calculate and display the value accordingly | K89: Calculation | L89: If (Invoice # !="") {Value="Billed"} else {Value="Pending"}
A90: + | C90: 90 | E90: invoice | F90: Billing Month | H90: FOCUS | I90: Invoiced Month | J90: Month Name with Year(Eg: Jun-2025) for the column Issue Date for the Serial Nos which is mentioned on Invoice #(Row 88) seperated by "|" | K90: Available | L90: Month Name with Year(Eg: Jun-2025) for the column Issue Date for the Serial Nos which is mentioned on Invoice #(Row 88) seperated by "|"
A91: + | C91: 91 | E91: invoice | F91: GRN | H91: COMS | I91: GRN | K91: Available
A92: + | C92: 92 | E92: invoice | F92: GRN STATUS | H92: COMS | I92: GRN Status | K92: Available | L92: If GRN# recorded then show it as "Complete" else show as "Pending".
C93: 93 | F93: PAYMENT STATUS | H93: DAX | I93: Payment Status of the InvoiceDebit Note No | K93: Not Required
A94: + | C94: 94 | E94: addl | F94: ADDL PO | H94: COMS | I94: ADDL PO | K94: Available
C95: 95 | F95: ADDL INV CHGS | H95: FOCUS | I95: Total Expected Revenue of Charges from focus__costs_revenues_items table which is configured in COMS Ancillary Charge Master based on Service in AED | J95: Total Expected Revenue of Charges from focus__costs_revenues_items table corresponding to the shipment’s serial number. These charges should be identified based on the Service (air_inbound, air_outbound, sea_inbound, etc.) as configured in the Charge Service Mapping table as category="Ancillary Charge" | K95: Not Required | L95: Total Expected Revenue= focus__costs_revenues_items.Selling Rate* focus__costs_revenues_items.Selling Quantity* focus__costs_revenues_items.Selling Local Exchange Rate
A96: + | C96: 96 | E96: addl | F96: ADDL INV # | G96: reverse of the Invoice # row | H96: FOCUS | I96: InvoiceDebit Note No of the Ancilliary Charges | J96: Fetch the Serial No from the focus__issued_invoices table where Voided = False, for the charges listed in the focus__costs_revenues_items table corresponding to the shipment’s serial number. These charges should be identified based on the Service (air_inbound, air_outbound, sea_inbound, etc.) as configured in the Charge Service Mapping table as category="Ancillary Charge", and the multiple focus__issued_invoices.Serial Number should be returned separated by "|" | K96: Available | L96: Fetch the Serial No from the focus__issued_invoices table where Voided = False, for the charges listed in the focus__costs_revenues_items table corresponding to the shipment’s serial number. These charges should be identified based on the Service (air_inbound, air_outbound, sea_inbound, etc.) as configured in the Charge Service Mapping table as category="Ancillary Charge", and the multiple focus__issued_invoices.Serial Number should be returned separated by "|"
A97: + | C97: 97 | E97: addl | F97: ADDL PO GRN # | H97: COMS | I97: ADDL PO GRN # | K97: Available
A98: + | C98: 98 | E98: addl | F98: ADDL INV BILLING MONTH | H98: FOCUS | I98: Pick from Billing Month of the field "ADDL INV #" generated from FOCUS | J98: Month Name with Year(Eg: Jun-2025) for the column Issue Date under for the Serial Nos which is mentioned on ADDL INV #(Row 96) seperated by "|" | K98: Available | L98: Month Name with Year(Eg: Jun-2025) for the column Issue Date under for the Serial Nos which is mentioned on ADDL INV # seperated by "|"
C99: 99 | E99: addl | F99: ADDL INV PAYMENT STATUS | H99: DAX | I99: Payment Status against the value on Additional Invoice#(ADDL INV #) column. | K99: Not Required
A100: + | C100: 100 | E100: metrics | F100: Days Delayed - ETD | H100: COMS | I100: COMS Tracker to calculate and display the value accordingly | K100: Calculation | L100: if(DeliveryDate="") {Value=""} else {Value=REVISED ETD-ETD} | M100: • REVISED ETD = ETD • ETD = PTD(Wakeo)
...

Sheet PBI Param list
A1: column_name
A2: _20_ft
A3: _40_ft
A4: _aux_chrg_aed
A5: _aux_chrg_usd
A6: _arrival_date
A7: _cargo_ho
A8: _crd
A9: _est_cargo_ready_date
A10: _carrier
A11: _cbm
A12: _chargeable_weight
... A84: _teus

Sheet SQL output
A1: SQL cols | B1: Exists? | C1: Needed?
A2: _fo_id | B2: =IFERROR(VLOOKUP(A2,'PBI Param list'!$A$2:$A$84,1,0),"_______OOPS______") -> _______OOPS______ | C2: no
A3: _shipment_serial_iss_job | B3: =IFERROR(VLOOKUP(A3,'PBI Param list'!$A$2:$A$84,1,0),"_______OOPS______") -> _shipment_serial_iss_job | C3: yes
A4: _branch_bu | B4: =IFERROR(VLOOKUP(A4,'PBI Param list'!$A$2:$A$84,1,0),"_______OOPS______") -> _______OOPS______ | C4: yes
A5: _fe_id | B5: =IFERROR(VLOOKUP(A5,'PBI Param list'!$A$2:$A$84,1,0),"_______OOPS______") -> _______OOPS______ | C5: no
A6: _pid | B6: =IFERROR(VLOOKUP(A6,'PBI Param list'!$A$2:$A$84,1,0),"_______OOPS______") -> _pid | C6: yes
A7: _supplier_code | B7: =IFERROR(VLOOKUP(A7,'PBI Param list'!$A$2:$A$84,1,0),"_______OOPS______") -> _supplier_code | C7: yes
A8: _supplier_name | B8: =IFERROR(VLOOKUP(A8,'PBI Param list'!$A$2:$A$84,1,0),"_______OOPS______") -> _supplier_name | C8: yes
A9: _po_no_ekporef | B9: =IFERROR(VLOOKUP(A9,'PBI Param list'!$A$2:$A$84,1,0),"_______OOPS______") -> _po_no_ekporef | C9: yes
A10: _secondary_po | B10: =IFERROR(VLOOKUP(A10,'PBI Param list'!$A$2:$A$84,1,0),"_______OOPS______") -> _secondary_po | C10: yes
A11: _po_remarks | B11: =IFERROR(VLOOKUP(A11,'PBI Param list'!$A$2:$A$84,1,0),"_______OOPS______") -> _po_remarks | C11: yes
A12: _commodity | B12: =IFERROR(VLOOKUP(A12,'PBI Param list'!$A$2:$A$84,1,0),"_______OOPS______") -> _commodity | C12: yes
A13: _iss_ref | B13: =IFERROR(VLOOKUP(A13,'PBI Param list'!$A$2:$A$84,1,0),"_______OOPS______") -> _iss_ref | C13: yes
... A121: _row_type | B121: =IFERROR(VLOOKUP(A121,'PBI Param list'!$A$2:$A$84,1,0),"_______OOPS______") -> _row_type | C121: no
