Workbook

Sheet Tracker
A1: S. NO. | B1: BU | C1: Supplier | D1: EKPOREF# | E1: SECONDARY PO | F1: PO REMARKS | G1: COMMODITY | H1: ISS REF | I1: MODE | J1: ROUTED BY | K1: INCOTERMS | L1: ISS JOB# | M1: HB/L/HAWB # | N1: MBL/MAWB # | O1: CONTAINER # | P1: POL | Q1: PORT NAME | R1: ORG COUNTRY | S1: ORG REGION | T1: DEST | U1: EQPT TYPE | V1: 20' | W1: 40' | X1: # OF CONT. | Y1: # of TEU's | Z1: Carrier | AA1: PR APPR DATE | AB1: PO APPR DATE | AC1: PO CREATION DATE | AD1: PO RECD DATE | AE1: PO NEED BY DATE | AF1: CRD | AG1: Pick Up | AH1: Cargo H/O | AI1: ETD | AJ1: REVISED ETD | AK1: ETA | AL1: REVISED ETA | AM1: D/O EXP | AN1: DEL | AO1: STATUS | AP1: DELIVERY LOCATION | AQ1: INNER QTY | AR1: CBM | AS1: G/W (KGS.) | AT1: C/W (KGS.) | AU1: QTY | AV1: PACK TYPE | AW1: Invoice (AED) | AX1: SHIPMENT REMARKS/UPDATES | AY1: P/A Sent | AZ1: D/N | BA1: ON TIME ORDER PLACEMENT PERF % | BB1: Supplier committed product readiness performance % | BC1: ISS container booking performance % | BD1: ISS Transit Lead Time Perf % | BE1: ISS custom clearance Perf % | BF1: E2E TOTAL LEAD TIME ACCURACY | BG1: No of Days Total Comm LT (as per contract) | BH1: Actual Lead (PO to Date) | BI1: HEALTH CHECK | BJ1: REASON CODE | BK1: No of Days Order Placement LT | BL1: No of Days Supplier Production Lead Time | BM1: No of Days Custom Clearance LT | BN1: No of Days ISS Cont Booking LT | BO1: No of Days Transit LT | BP1: E2E Total LT | BQ1: ORG CHARGES (USD) | BR1: FRT CHGS (USD) | BS1: DEST CHARGES (USD) | BT1: Ancillary Charges (AED) | BU1: Ancillary Charge Type | BV1: ORG CHGS (AED) | BW1: FRT CHGS (AED) | BX1: DEST CHGS (AED) | BY1: P2P VALUE | BZ1: TOTAL CHARGES (AED) | CA1: REQUISITION / BILLING NOTES | CB1: PR # | CC1: PR DATE | CD1: REQ STATUS | CE1: SPO # | CF1: PO STATUS | CG1: SPO /Inv Val(AED) | CH1: Sent to OPS | CI1: Invoice # | CJ1: Billing Status | CK1: Billing Month | CL1: GRN | CM1: GRN STATUS | CN1: PAYMENT STATUS | CO1: ADDL PO | CP1: ADDL INV CHGS | CQ1: ADDL INV # | CR1: ADDL PO GRN # | CS1: ADDL INV BILLING MONTH | CT1: ADDL INV PAYMENT STATUS | CU1: Days Delayed - ETD | CV1: Days Delayed - ETA | CW1: RDD-ETA | CX1: Invoice ( USD) | CY1: NBD TO CRD | CZ1: PO TO CRD (Supplier Response) | DA1: CRD TO ETD | DB1: ETD TO ETA | DC1: ETA TO DEL | DD1: NBD TO ETA | DE1: NBD TO DEL | DF1: AVERAGE LT | DG1: BILLING REPORT | DH1: Ancilliary Charge Form No
C2: IACOBUCCI HF AEROSPACE S.P.A. | D2: 422007642-18 | F2: Revised PO to add extra quantity | G2: STEAM SPOUT | AA2: 45939 | AB2: 45944 | AC2: 45945 | AD2: 45946 | AE2: 46019 | AO2: Pending | AQ2: 43200 | BA2: =IF(Table1[[#This Row],[PO APPR DATE]]>0,IF(Table1[[#This Row],[PO APPR DATE]]-Table1[[#This Row],[PR APPR DATE]]<=5,1,1-ABS(Table1[[#This Row],[PO APPR DATE]]-Table1[[#This Row],[PR APPR DATE]])/5),0) -> 1 | BB2: {=IFERROR(_xlfn.IFS(ISBLANK(Table1[[#This Row],[PO APPR DATE]]),0,Table1[[#This Row],[CRD]]="",0,Table1[[#This Row],[CRD]]-Table1[[#This Row],[PO APPR DATE]]<=VLOOKUP(Table1[[#This Row],[Supplier ]],SupplierLeadTimeMaster!$A$2:$B$235,2,0),1,(Table1[[#This Row],[CRD]]-Table1[[#This Row],[PO APPR DATE]])>VLOOKUP(Table1[[#This Row],[Supplier ]],SupplierLeadTimeMaster!$A$2:$B$235,2,0),1-ABS(Table1[[#This Row],[CRD]]-Table1[[#This Row],[PO APPR DATE]])/VLOOKUP(Table1[[#This Row],[Supplier ]],SupplierLeadTimeMaster!$A$2:$B$235,2,0)),"")} -> 0 | BC2: =IFERROR(IF(AND(Table1[[#This Row],[ETD]]>0,Table1[[#This Row],[No of Days ISS Cont Booking LT]]>0),IF((Table1[[#This Row],[ETD]]-Table1[[#This Row],[CRD]])<=7,1,1-ABS(Table1[[#This Row],[ETD]]-Table1[[#This Row],[CRD]])/7),0),"") -> 0 | BD2: {=_xlfn.IFS(Table1[[#This Row],[DEL]]="",0,Table1[[#This Row],[ORG COUNTRY]]="",0,ISBLANK(Table1[[#This Row],[ETD]]),0,Table1[[#This Row],[ETA]]="",0,Table1[[#This Row],[ETA]]-Table1[[#This Row],[ETD]]<=VLOOKUP(Table1[[#This Row],[ORG COUNTRY]],CountryTransitTimeMaster!$B$2:$C$44,2,FALSE),1,Table1[[#This Row],[ETA]]-Table1[[#This Row],[ETD]]>VLOOKUP(Table1[[#This Row],[ORG COUNTRY]],CountryTransitTimeMaster!$B$2:$C$44,2,FALSE),1-ABS(Table1[[#This Row],[ETA]]-Table1[[#This Row],[ETD]])/VLOOKUP(Table1[[#This Row],[ORG COUNTRY]],CountryTransitTimeMaster!$B$2:$C$44,2,FALSE))} -> 0 | BE2: {=_xlfn.IFS(Table1[[#This Row],[DEL]]="",0,ISBLANK(Table1[[#This Row],[DEL]]),0,Table1[[#This Row],[DEL]]-Table1[[#This Row],[ETA]]<=3,1,(Table1[[#This Row],[DEL]]-Table1[[#This Row],[ETA]])>3,1-ABS(Table1[[#This Row],[DEL]]-Table1[[#This Row],[ETA]])/3)} -> 0 | BF2: =IFERROR(IF(Table1[[#This Row],[E2E Total LT]]>0,1-ABS(Table1[[#This Row],[E2E Total LT]]-Table1[[#This Row],[No of Days Total Comm LT (as per contract)]])/Table1[[#This Row],[No of Days Total Comm LT (as per contract)]],0),"") -> 0 | BG2: {=_xlfn.IFS(Table1[[#This Row],[DEL]]="",0,Table1[[#This Row],[STATUS]]="Cancelled",0,Table1[[#This Row],[ORG COUNTRY]]="",0,ISNONTEXT(Table1[[#This Row],[DEL]]),SUM(VLOOKUP(Table1[[#This Row],[Supplier ]],SupplierLeadTimeMaster!$A$2:$B$235,2,FALSE),VLOOKUP(Table1[[#This Row],[ORG COUNTRY]],CountryTransitTimeMaster!$B$2:$C$44,2,FALSE),7,3,5))} -> 0 | BH2: =IFERROR(IF(SUM(Table1[[#This Row],[No of Days Order Placement LT]],Table1[[#This Row],[No of Days Supplier Production Lead Time]],Table1[[#This Row],[No of Days Custom Clearance LT]],Table1[[#This Row],[No of Days ISS Cont Booking LT]],Table1[[#This Row],[No of Days Transit LT]])>500,0,SUM(Table1[[#This Row],[No of Days Order Placement LT]],Table1[[#This Row],[No of Days Supplier Production Lead Time]],Table1[[#This Row],[No of Days Custom Clearance LT]],Table1[[#This Row],[No of Days ISS Cont Booking LT]],Table1[[#This Row],[No of Days Transit LT]])),0) -> 5 | BI2: {=IFERROR(_xlfn.IFS((Table1[[#This Row],[No of Days Supplier Production Lead Time]])=" "," ",Table1[[#This Row],[Actual Lead (PO to Date)]]-Table1[[#This Row],[No of Days Total Comm LT (as per contract)]]<=15,"Healthy",Table1[[#This Row],[Actual Lead (PO to Date)]]-Table1[[#This Row],[No of Days Total Comm LT (as per contract)]]<=30,"Minor",Table1[[#This Row],[Actual Lead (PO to Date)]]-Table1[[#This Row],[No of Days Total Comm LT (as per contract)]]<=45,"Moderate",Table1[[#This Row],[Actual Lead (PO to Date)]]-Table1[[#This Row],[No of Days Total Comm LT (as per contract)]]<=60,"Major",Table1[[#This Row],[Actual Lead (PO to Date)]]-Table1[[#This Row],[No of Days Total Comm LT (as per contract)]]>60,"Severe",ISBLANK(Table1[[#This Row],[DEL]])," ",ISBLANK(Table1[[#This Row],[ETA]])," ",ISBLANK(Table1[[#This Row],[ETD]])," ",ISBLANK(Table1[[#This Row],[PR APPR DATE]])," ",ISBLANK(Table1[[#This Row],[Actual Lead (PO to Date)]])," ",ISBLANK(Table1[[#This Row],[No of Days Total Comm LT (as per contract)]])," ")," ")} -> Healthy | BJ2: {=IFERROR(_xlfn.IFS(Table1[[#This Row],[HEALTH CHECK]]=" ","",Table1[[#This Row],[HEALTH CHECK]]="Healthy"," ",Table1[[#This Row],[ON TIME ORDER PLACEMENT PERF %]]<100%,"PR to PO Delay",Table1[[#This Row],[Supplier committed product readiness performance % ]]<100%,"Product Readiness Delay",Table1[[#This Row],[ISS container booking performance %]]<100%,"Booking Delay",Table1[[#This Row],[ISS Transit Lead Time Perf %]]<100%,"Trans Shipment Delay",Table1[[#This Row],[ISS custom clearance Perf % ]]<100%,"Custom Clearance Delay")," ")} | BK2: {=_xlfn.IFS(ISBLANK(Table1[[#This Row],[PR APPR DATE]]),0,ISBLANK(Table1[[#This Row],[PO APPR DATE]]),0,ISNONTEXT(Table1[[#This Row],[PO APPR DATE]]),Table1[[#This Row],[PO APPR DATE]]-Table1[[#This Row],[PR APPR DATE]])} -> 5 | BL2: {=_xlfn.IFS((Table1[[#This Row],[DEL]])="",0,ISBLANK(Table1[[#This Row],[CRD]]),0,ISBLANK(Table1[[#This Row],[PO APPR DATE]]),0,ISNONTEXT(Table1[[#This Row],[PO APPR DATE]]),Table1[[#This Row],[CRD]]-Table1[[#This Row],[PO APPR DATE]])} -> 0 | BM2: =IFERROR(IF(Table1[[#This Row],[DEL]]>0,Table1[[#This Row],[DEL]]-Table1[[#This Row],[ETA]],0),0) -> 0 | BN2: =IFERROR(IF(Table1[[#This Row],[ETD]]>0,(Table1[[#This Row],[ETD]]-Table1[[#This Row],[CRD]]),0),"") -> 0 | BO2: =IFERROR(IF(Table1[[#This Row],[ETA]]>0,(Table1[[#This Row],[ETA]]-Table1[[#This Row],[ETD]]),0),0) -> 0 | BP2: {=_xlfn.IFS(Table1[[#This Row],[DEL]]="",0,Table1[[#This Row],[DEL]]="",0,ISBLANK(Table1[[#This Row],[PR APPR DATE]]),0,ISBLANK(Table1[[#This Row],[DEL]]),0,ISNONTEXT(Table1[[#This Row],[PR APPR DATE]]),Table1[[#This Row],[DEL]]-Table1[[#This Row],[PR APPR DATE]],Table1[[#This Row],[DEL]]="",0)} -> 0 | BQ2: =Table1[[#This Row],[ORG CHGS (AED)]]/3.673 -> 0 | BR2: =Table1[[#This Row],[FRT CHGS (AED)]]/3.673 -> 0 | BS2: =Table1[[#This Row],[DEST CHGS (AED)]]/3.673 -> 0 | BY2: =SUM(Table1[[#This Row],[ORG CHGS (AED)]],Table1[[#This Row],[FRT CHGS (AED)]],Table1[[#This Row],[DEST CHGS (AED)]]) -> 0 | BZ2: =SUM(Table1[[#This Row],[P2P VALUE]]+Table1[[#This Row],[Ancillary Charges (AED)]]) -> 0 | CD2: =IF(ISBLANK(Table1[[#This Row],[PR DATE]]),"Pending","Logged") -> Pending | CF2: =IF(ISBLANK(Table1[[#This Row],[SPO '#]]),"Pending","Received") -> Pending | CJ2: {=_xlfn.IFS(ISTEXT(Table1[[#This Row],[Invoice '#]]),"Billed",Table1[[#This Row],[PO STATUS]]="Received","Pending",Table1[[#This Row],[PO STATUS]]="Pending","Pending")} -> Pending | CM2: =IF(ISBLANK(Table1[[#This Row],[GRN]]),"Pending","Complete") -> Pending | CU2: =IF(Table1[[#This Row],[DEL]]="","",Table1[[#This Row],[REVISED ETD]]-Table1[[#This Row],[ETD]]) | CV2: =IF(Table1[[#This Row],[DEL]]="","",Table1[[#This Row],[REVISED ETA]]-Table1[[#This Row],[ETA]]) | CW2: =IF(Table1[[#This Row],[DEL]]="","",Table1[[#This Row],[ETA]]-Table1[[#This Row],[PO NEED BY DATE]]) | CX2: =Table1[[#This Row],[Invoice (AED)]]/3.673 -> 0 | CY2: {=_xlfn.IFS(Table1[[#This Row],[STATUS]]="Cancelled",,Table1[[#This Row],[STATUS]]="Pending",,Table1[[#This Row],[STATUS]]="Not Due",,ISNONTEXT(Table1[[#This Row],[CRD]]),Table1[[#This Row],[CRD]]-Table1[[#This Row],[PO NEED BY DATE]])} -> 0 | CZ2: =IF(Table1[[#This Row],[CRD]]<>"", Table1[[#This Row],[CRD]]-Table1[[#This Row],[PO CREATION DATE]], 0) -> 0 | DA2: =IF(Table1[[#This Row],[REVISED ETD]]<>"", Table1[[#This Row],[REVISED ETD]]-Table1[[#This Row],[CRD]], Table1[[#This Row],[ETD]]-Table1[[#This Row],[CRD]]) -> 0 | DB2: =IF(AND(Table1[[#This Row],[REVISED ETD]]<>"", Table1[[#This Row],[REVISED ETA]]<>""), Table1[[#This Row],[REVISED ETA]]-Table1[[#This Row],[REVISED ETD]], IF(AND(Table1[[#This Row],[REVISED ETA]]<>"", Table1[[#This Row],[REVISED ETD]]=""), Table1[[#This Row],[REVISED ETA]]-Table1[[#This Row],[ETD]], IF(AND(Table1[[#This Row],[REVISED ETA]]="", Table1[[#This Row],[REVISED ETD]]<>""), Table1[[#This Row],[ETA]]-Table1[[#This Row],[REVISED ETD]], IF(AND(Table1[[#This Row],[REVISED ETA]]="", Table1[[#This Row],[REVISED ETD]]=""), Table1[[#This Row],[ETA]]-Table1[[#This Row],[ETD]], "") ) ) ) -> 0 | DC2: =IF(Table1[[#This Row],[REVISED ETA]]<>"", Table1[[#This Row],[DEL]]-Table1[[#This Row],[REVISED ETA]], Table1[[#This Row],[DEL]]-Table1[[#This Row],[ETA]]) -> 0 | DD2: {=_xlfn.IFS(Table1[[#This Row],[STATUS]]="Cancelled",,Table1[[#This Row],[STATUS]]="Pending",,Table1[[#This Row],[STATUS]]="Not Due",,ISNONTEXT(Table1[[#This Row],[ETD]]),Table1[[#This Row],[ETA]]-Table1[[#This Row],[PO NEED BY DATE]])} -> 0 | DE2: =Table1[[#This Row],[PO NEED BY DATE]]-Table1[[#This Row],[DEL]] -> 46019 | DF2: =SUM(Table1[[#This Row],[CRD TO ETD]],Table1[[#This Row],[ETD TO ETA]],Table1[[#This Row],[ETA TO DEL]],Table1[[#This Row],[NBD TO ETA]],Table1[[#This Row],[NBD TO DEL]]) -> 46019
C3: IACOBUCCI HF AEROSPACE S.P.A. | D3: 422007642-17 | F3: PO should be fulfilled | G3: STEAM SPOUT | AA3: 45945 | AB3: 45945 | AC3: 45945 | AD3: 45947 | AE3: 46021 | AO3: Pending | AQ3: 42600 | BA3: =IF(Table1[[#This Row],[PO APPR DATE]]>0,IF(Table1[[#This Row],[PO APPR DATE]]-Table1[[#This Row],[PR APPR DATE]]<=5,1,1-ABS(Table1[[#This Row],[PO APPR DATE]]-Table1[[#This Row],[PR APPR DATE]])/5),0) -> 1 | BB3: {=IFERROR(_xlfn.IFS(ISBLANK(Table1[[#This Row],[PO APPR DATE]]),0,Table1[[#This Row],[CRD]]="",0,Table1[[#This Row],[CRD]]-Table1[[#This Row],[PO APPR DATE]]<=VLOOKUP(Table1[[#This Row],[Supplier ]],SupplierLeadTimeMaster!$A$2:$B$235,2,0),1,(Table1[[#This Row],[CRD]]-Table1[[#This Row],[PO APPR DATE]])>VLOOKUP(Table1[[#This Row],[Supplier ]],SupplierLeadTimeMaster!$A$2:$B$235,2,0),1-ABS(Table1[[#This Row],[CRD]]-Table1[[#This Row],[PO APPR DATE]])/VLOOKUP(Table1[[#This Row],[Supplier ]],SupplierLeadTimeMaster!$A$2:$B$235,2,0)),"")} -> 0 | BC3: =IFERROR(IF(AND(Table1[[#This Row],[ETD]]>0,Table1[[#This Row],[No of Days ISS Cont Booking LT]]>0),IF((Table1[[#This Row],[ETD]]-Table1[[#This Row],[CRD]])<=7,1,1-ABS(Table1[[#This Row],[ETD]]-Table1[[#This Row],[CRD]])/7),0),"") -> 0 | BD3: {=_xlfn.IFS(Table1[[#This Row],[DEL]]="",0,Table1[[#This Row],[ORG COUNTRY]]="",0,ISBLANK(Table1[[#This Row],[ETD]]),0,Table1[[#This Row],[ETA]]="",0,Table1[[#This Row],[ETA]]-Table1[[#This Row],[ETD]]<=VLOOKUP(Table1[[#This Row],[ORG COUNTRY]],CountryTransitTimeMaster!$B$2:$C$44,2,FALSE),1,Table1[[#This Row],[ETA]]-Table1[[#This Row],[ETD]]>VLOOKUP(Table1[[#This Row],[ORG COUNTRY]],CountryTransitTimeMaster!$B$2:$C$44,2,FALSE),1-ABS(Table1[[#This Row],[ETA]]-Table1[[#This Row],[ETD]])/VLOOKUP(Table1[[#This Row],[ORG COUNTRY]],CountryTransitTimeMaster!$B$2:$C$44,2,FALSE))} -> 0 | BE3: {=_xlfn.IFS(Table1[[#This Row],[DEL]]="",0,ISBLANK(Table1[[#This Row],[DEL]]),0,Table1[[#This Row],[DEL]]-Table1[[#This Row],[ETA]]<=3,1,(Table1[[#This Row],[DEL]]-Table1[[#This Row],[ETA]])>3,1-ABS(Table1[[#This Row],[DEL]]-Table1[[#This Row],[ETA]])/3)} -> 0 | BF3: =IFERROR(IF(Table1[[#This Row],[E2E Total LT]]>0,1-ABS(Table1[[#This Row],[E2E Total LT]]-Table1[[#This Row],[No of Days Total Comm LT (as per contract)]])/Table1[[#This Row],[No of Days Total Comm LT (as per contract)]],0),"") -> 0 | BG3: {=_xlfn.IFS(Table1[[#This Row],[DEL]]="",0,Table1[[#This Row],[STATUS]]="Cancelled",0,Table1[[#This Row],[ORG COUNTRY]]="",0,ISNONTEXT(Table1[[#This Row],[DEL]]),SUM(VLOOKUP(Table1[[#This Row],[Supplier ]],SupplierLeadTimeMaster!$A$2:$B$235,2,FALSE),VLOOKUP(Table1[[#This Row],[ORG COUNTRY]],CountryTransitTimeMaster!$B$2:$C$44,2,FALSE),7,3,5))} -> 0 | BH3: =IFERROR(IF(SUM(Table1[[#This Row],[No of Days Order Placement LT]],Table1[[#This Row],[No of Days Supplier Production Lead Time]],Table1[[#This Row],[No of Days Custom Clearance LT]],Table1[[#This Row],[No of Days ISS Cont Booking LT]],Table1[[#This Row],[No of Days Transit LT]])>500,0,SUM(Table1[[#This Row],[No of Days Order Placement LT]],Table1[[#This Row],[No of Days Supplier Production Lead Time]],Table1[[#This Row],[No of Days Custom Clearance LT]],Table1[[#This Row],[No of Days ISS Cont Booking LT]],Table1[[#This Row],[No of Days Transit LT]])),0) -> 0 | BI3: {=IFERROR(_xlfn.IFS((Table1[[#This Row],[No of Days Supplier Production Lead Time]])=" "," ",Table1[[#This Row],[Actual Lead (PO to Date)]]-Table1[[#This Row],[No of Days Total Comm LT (as per contract)]]<=15,"Healthy",Table1[[#This Row],[Actual Lead (PO to Date)]]-Table1[[#This Row],[No of Days Total Comm LT (as per contract)]]<=30,"Minor",Table1[[#This Row],[Actual Lead (PO to Date)]]-Table1[[#This Row],[No of Days Total Comm LT (as per contract)]]<=45,"Moderate",Table1[[#This Row],[Actual Lead (PO to Date)]]-Table1[[#This Row],[No of Days Total Comm LT (as per contract)]]<=60,"Major",Table1[[#This Row],[Actual Lead (PO to Date)]]-Table1[[#This Row],[No of Days Total Comm LT (as per contract)]]>60,"Severe",ISBLANK(Table1[[#This Row],[DEL]])," ",ISBLANK(Table1[[#This Row],[ETA]])," ",ISBLANK(Table1[[#This Row],[ETD]])," ",ISBLANK(Table1[[#This Row],[PR APPR DATE]])," ",ISBLANK(Table1[[#This Row],[Actual Lead (PO to Date)]])," ",ISBLANK(Table1[[#This Row],[No of Days Total Comm LT (as per contract)]])," ")," ")} -> Healthy | BJ3: {=IFERROR(_xlfn.IFS(Table1[[#This Row],[HEALTH CHECK]]=" ","",Table1[[#This Row],[HEALTH CHECK]]="Healthy"," ",Table1[[#This Row],[ON TIME ORDER PLACEMENT PERF %]]<100%,"PR to PO Delay",Table1[[#This Row],[Supplier committed product readiness performance % ]]<100%,"Product Readiness Delay",Table1[[#This Row],[ISS container booking performance %]]<100%,"Booking Delay",Table1[[#This Row],[ISS Transit Lead Time Perf %]]<100%,"Trans Shipment Delay",Table1[[#This Row],[ISS custom clearance Perf % ]]<100%,"Custom Clearance Delay")," ")} | BK3: {=_xlfn.IFS(ISBLANK(Table1[[#This Row],[PR APPR DATE]]),0,ISBLANK(Table1[[#This Row],[PO APPR DATE]]),0,ISNONTEXT(Table1[[#This Row],[PO APPR DATE]]),Table1[[#This Row],[PO APPR DATE]]-Table1[[#This Row],[PR APPR DATE]])} -> 0 | BL3: {=_xlfn.IFS((Table1[[#This Row],[DEL]])="",0,ISBLANK(Table1[[#This Row],[CRD]]),0,ISBLANK(Table1[[#This Row],[PO APPR DATE]]),0,ISNONTEXT(Table1[[#This Row],[PO APPR DATE]]),Table1[[#This Row],[CRD]]-Table1[[#This Row],[PO APPR DATE]])} -> 0 | BM3: =IFERROR(IF(Table1[[#This Row],[DEL]]>0,Table1[[#This Row],[DEL]]-Table1[[#This Row],[ETA]],0),0) -> 0 | BN3: =IFERROR(IF(Table1[[#This Row],[ETD]]>0,(Table1[[#This Row],[ETD]]-Table1[[#This Row],[CRD]]),0),"") -> 0 | BO3: =IFERROR(IF(Table1[[#This Row],[ETA]]>0,(Table1[[#This Row],[ETA]]-Table1[[#This Row],[ETD]]),0),0) -> 0 | BP3: {=_xlfn.IFS(Table1[[#This Row],[DEL]]="",0,Table1[[#This Row],[DEL]]="",0,ISBLANK(Table1[[#This Row],[PR APPR DATE]]),0,ISBLANK(Table1[[#This Row],[DEL]]),0,ISNONTEXT(Table1[[#This Row],[PR APPR DATE]]),Table1[[#This Row],[DEL]]-Table1[[#This Row],[PR APPR DATE]],Table1[[#This Row],[DEL]]="",0)} -> 0 | BQ3: =Table1[[#This Row],[ORG CHGS (AED)]]/3.673 -> 0 | BR3: =Table1[[#This Row],[FRT CHGS (AED)]]/3.673 -> 0 | BS3: =Table1[[#This Row],[DEST CHGS (AED)]]/3.673 -> 0 | BY3: =SUM(Table1[[#This Row],[ORG CHGS (AED)]],Table1[[#This Row],[FRT CHGS (AED)]],Table1[[#This Row],[DEST CHGS (AED)]]) -> 0 | BZ3: =SUM(Table1[[#This Row],[P2P VALUE]]+Table1[[#This Row],[Ancillary Charges (AED)]]) -> 0 | CD3: =IF(ISBLANK(Table1[[#This Row],[PR DATE]]),"Pending","Logged") -> Pending | CF3: =IF(ISBLANK(Table1[[#This Row],[SPO '#]]),"Pending","Received") -> Pending | CJ3: {=_xlfn.IFS(ISTEXT(Table1[[#This Row],[Invoice '#]]),"Billed",Table1[[#This Row],[PO STATUS]]="Received","Pending",Table1[[#This Row],[PO STATUS]]="Pending","Pending")} -> Pending | CM3: =IF(ISBLANK(Table1[[#This Row],[GRN]]),"Pending","Complete") -> Pending | CU3: =IF(Table1[[#This Row],[DEL]]="","",Table1[[#This Row],[REVISED ETD]]-Table1[[#This Row],[ETD]]) | CV3: =IF(Table1[[#This Row],[DEL]]="","",Table1[[#This Row],[REVISED ETA]]-Table1[[#This Row],[ETA]]) | CW3: =IF(Table1[[#This Row],[DEL]]="","",Table1[[#This Row],[ETA]]-Table1[[#This Row],[PO NEED BY DATE]]) | CX3: =Table1[[#This Row],[Invoice (AED)]]/3.673 -> 0 | CY3: {=_xlfn.IFS(Table1[[#This Row],[STATUS]]="Cancelled",,Table1[[#This Row],[STATUS]]="Pending",,Table1[[#This Row],[STATUS]]="Not Due",,ISNONTEXT(Table1[[#This Row],[CRD]]),Table1[[#This Row],[CRD]]-Table1[[#This Row],[PO NEED BY DATE]])} -> 0 | CZ3: =IF(Table1[[#This Row],[CRD]]<>"", Table1[[#This Row],[CRD]]-Table1[[#This Row],[PO CREATION DATE]], 0) -> 0 | DA3: =IF(Table1[[#This Row],[REVISED ETD]]<>"", Table1[[#This Row],[REVISED ETD]]-Table1[[#This Row],[CRD]], Table1[[#This Row],[ETD]]-Table1[[#This Row],[CRD]]) -> 0 | DB3: =IF(AND(Table1[[#This Row],[REVISED ETD]]<>"", Table1[[#This Row],[REVISED ETA]]<>""), Table1[[#This Row],[REVISED ETA]]-Table1[[#This Row],[REVISED ETD]], IF(AND(Table1[[#This Row],[REVISED ETA]]<>"", Table1[[#This Row],[REVISED ETD]]=""), Table1[[#This Row],[REVISED ETA]]-Table1[[#This Row],[ETD]], IF(AND(Table1[[#This Row],[REVISED ETA]]="", Table1[[#This Row],[REVISED ETD]]<>""), Table1[[#This Row],[ETA]]-Table1[[#This Row],[REVISED ETD]], IF(AND(Table1[[#This Row],[REVISED ETA]]="", Table1[[#This Row],[REVISED ETD]]=""), Table1[[#This Row],[ETA]]-Table1[[#This Row],[ETD]], "") ) ) ) -> 0 | DC3: =IF(Table1[[#This Row],[REVISED ETA]]<>"", Table1[[#This Row],[DEL]]-Table1[[#This Row],[REVISED ETA]], Table1[[#This Row],[DEL]]-Table1[[#This Row],[ETA]]) -> 0 | DD3: {=_xlfn.IFS(Table1[[#This Row],[STATUS]]="Cancelled",,Table1[[#This Row],[STATUS]]="Pending",,Table1[[#This Row],[STATUS]]="Not Due",,ISNONTEXT(Table1[[#This Row],[ETD]]),Table1[[#This Row],[ETA]]-Table1[[#This Row],[PO NEED BY DATE]])} -> 0 | DE3: =Table1[[#This Row],[PO NEED BY DATE]]-Table1[[#This Row],[DEL]] -> 46021 | DF3: =SUM(Table1[[#This Row],[CRD TO ETD]],Table1[[#This Row],[ETD TO ETA]],Table1[[#This Row],[ETA TO DEL]],Table1[[#This Row],[NBD TO ETA]],Table1[[#This Row],[NBD TO DEL]]) -> 46021
C4: AL SALEM TRADING ENTERPRISES L.L.C. | D4: 422015518-963 | F4: woven covers po | G4: Non-woven Covers for Headrest, Pillow | AA4: 45945 | AB4: 45945 | AC4: 45945 | AD4: 45947 | AE4: 45948 | AO4: Cancelled | AQ4: 90000 | BA4: =IF(Table1[[#This Row],[PO APPR DATE]]>0,IF(Table1[[#This Row],[PO APPR DATE]]-Table1[[#This Row],[PR APPR DATE]]<=5,1,1-ABS(Table1[[#This Row],[PO APPR DATE]]-Table1[[#This Row],[PR APPR DATE]])/5),0) -> 1 | BB4: {=IFERROR(_xlfn.IFS(ISBLANK(Table1[[#This Row],[PO APPR DATE]]),0,Table1[[#This Row],[CRD]]="",0,Table1[[#This Row],[CRD]]-Table1[[#This Row],[PO APPR DATE]]<=VLOOKUP(Table1[[#This Row],[Supplier ]],SupplierLeadTimeMaster!$A$2:$B$235,2,0),1,(Table1[[#This Row],[CRD]]-Table1[[#This Row],[PO APPR DATE]])>VLOOKUP(Table1[[#This Row],[Supplier ]],SupplierLeadTimeMaster!$A$2:$B$235,2,0),1-ABS(Table1[[#This Row],[CRD]]-Table1[[#This Row],[PO APPR DATE]])/VLOOKUP(Table1[[#This Row],[Supplier ]],SupplierLeadTimeMaster!$A$2:$B$235,2,0)),"")} -> 0 | BC4: =IFERROR(IF(AND(Table1[[#This Row],[ETD]]>0,Table1[[#This Row],[No of Days ISS Cont Booking LT]]>0),IF((Table1[[#This Row],[ETD]]-Table1[[#This Row],[CRD]])<=7,1,1-ABS(Table1[[#This Row],[ETD]]-Table1[[#This Row],[CRD]])/7),0),"") -> 0 | BD4: {=_xlfn.IFS(Table1[[#This Row],[DEL]]="",0,Table1[[#This Row],[ORG COUNTRY]]="",0,ISBLANK(Table1[[#This Row],[ETD]]),0,Table1[[#This Row],[ETA]]="",0,Table1[[#This Row],[ETA]]-Table1[[#This Row],[ETD]]<=VLOOKUP(Table1[[#This Row],[ORG COUNTRY]],CountryTransitTimeMaster!$B$2:$C$44,2,FALSE),1,Table1[[#This Row],[ETA]]-Table1[[#This Row],[ETD]]>VLOOKUP(Table1[[#This Row],[ORG COUNTRY]],CountryTransitTimeMaster!$B$2:$C$44,2,FALSE),1-ABS(Table1[[#This Row],[ETA]]-Table1[[#This Row],[ETD]])/VLOOKUP(Table1[[#This Row],[ORG COUNTRY]],CountryTransitTimeMaster!$B$2:$C$44,2,FALSE))} -> 0 | BE4: {=_xlfn.IFS(Table1[[#This Row],[DEL]]="",0,ISBLANK(Table1[[#This Row],[DEL]]),0,Table1[[#This Row],[DEL]]-Table1[[#This Row],[ETA]]<=3,1,(Table1[[#This Row],[DEL]]-Table1[[#This Row],[ETA]])>3,1-ABS(Table1[[#This Row],[DEL]]-Table1[[#This Row],[ETA]])/3)} -> 0 | BF4: =IFERROR(IF(Table1[[#This Row],[E2E Total LT]]>0,1-ABS(Table1[[#This Row],[E2E Total LT]]-Table1[[#This Row],[No of Days Total Comm LT (as per contract)]])/Table1[[#This Row],[No of Days Total Comm LT (as per contract)]],0),"") -> 0 | BG4: {=_xlfn.IFS(Table1[[#This Row],[DEL]]="",0,Table1[[#This Row],[STATUS]]="Cancelled",0,Table1[[#This Row],[ORG COUNTRY]]="",0,ISNONTEXT(Table1[[#This Row],[DEL]]),SUM(VLOOKUP(Table1[[#This Row],[Supplier ]],SupplierLeadTimeMaster!$A$2:$B$235,2,FALSE),VLOOKUP(Table1[[#This Row],[ORG COUNTRY]],CountryTransitTimeMaster!$B$2:$C$44,2,FALSE),7,3,5))} -> 0 | BH4: =IFERROR(IF(SUM(Table1[[#This Row],[No of Days Order Placement LT]],Table1[[#This Row],[No of Days Supplier Production Lead Time]],Table1[[#This Row],[No of Days Custom Clearance LT]],Table1[[#This Row],[No of Days ISS Cont Booking LT]],Table1[[#This Row],[No of Days Transit LT]])>500,0,SUM(Table1[[#This Row],[No of Days Order Placement LT]],Table1[[#This Row],[No of Days Supplier Production Lead Time]],Table1[[#This Row],[No of Days Custom Clearance LT]],Table1[[#This Row],[No of Days ISS Cont Booking LT]],Table1[[#This Row],[No of Days Transit LT]])),0) -> 0 | BI4: {=IFERROR(_xlfn.IFS((Table1[[#This Row],[No of Days Supplier Production Lead Time]])=" "," ",Table1[[#This Row],[Actual Lead (PO to Date)]]-Table1[[#This Row],[No of Days Total Comm LT (as per contract)]]<=15,"Healthy",Table1[[#This Row],[Actual Lead (PO to Date)]]-Table1[[#This Row],[No of Days Total Comm LT (as per contract)]]<=30,"Minor",Table1[[#This Row],[Actual Lead (PO to Date)]]-Table1[[#This Row],[No of Days Total Comm LT (as per contract)]]<=45,"Moderate",Table1[[#This Row],[Actual Lead (PO to Date)]]-Table1[[#This Row],[No of Days Total Comm LT (as per contract)]]<=60,"Major",Table1[[#This Row],[Actual Lead (PO to Date)]]-Table1[[#This Row],[No of Days Total Comm LT (as per contract)]]>60,"Severe",ISBLANK(Table1[[#This Row],[DEL]])," ",ISBLANK(Table1[[#This Row],[ETA]])," ",ISBLANK(Table1[[#This Row],[ETD]])," ",ISBLANK(Table1[[#This Row],[PR APPR DATE]])," ",ISBLANK(Table1[[#This Row],[Actual Lead (PO to Date)]])," ",ISBLANK(Table1[[#This Row],[No of Days Total Comm LT (as per contract)]])," ")," ")} -> Healthy | BJ4: {=IFERROR(_xlfn.IFS(Table1[[#This Row],[HEALTH CHECK]]=" ","",Table1[[#This Row],[HEALTH CHECK]]="Healthy"," ",Table1[[#This Row],[ON TIME ORDER PLACEMENT PERF %]]<100%,"PR to PO Delay",Table1[[#This Row],[Supplier committed product readiness performance % ]]<100%,"Product Readiness Delay",Table1[[#This Row],[ISS container booking performance %]]<100%,"Booking Delay",Table1[[#This Row],[ISS Transit Lead Time Perf %]]<100%,"Trans Shipment Delay",Table1[[#This Row],[ISS custom clearance Perf % ]]<100%,"Custom Clearance Delay")," ")} | BK4: {=_xlfn.IFS(ISBLANK(Table1[[#This Row],[PR APPR DATE]]),0,ISBLANK(Table1[[#This Row],[PO APPR DATE]]),0,ISNONTEXT(Table1[[#This Row],[PO APPR DATE]]),Table1[[#This Row],[PO APPR DATE]]-Table1[[#This Row],[PR APPR DATE]])} -> 0 | BL4: {=_xlfn.IFS((Table1[[#This Row],[DEL]])="",0,ISBLANK(Table1[[#This Row],[CRD]]),0,ISBLANK(Table1[[#This Row],[PO APPR DATE]]),0,ISNONTEXT(Table1[[#This Row],[PO APPR DATE]]),Table1[[#This Row],[CRD]]-Table1[[#This Row],[PO APPR DATE]])} -> 0 | BM4: =IFERROR(IF(Table1[[#This Row],[DEL]]>0,Table1[[#This Row],[DEL]]-Table1[[#This Row],[ETA]],0),0) -> 0 | BN4: =IFERROR(IF(Table1[[#This Row],[ETD]]>0,(Table1[[#This Row],[ETD]]-Table1[[#This Row],[CRD]]),0),"") -> 0 | BO4: =IFERROR(IF(Table1[[#This Row],[ETA]]>0,(Table1[[#This Row],[ETA]]-Table1[[#This Row],[ETD]]),0),0) -> 0 | BP4: {=_xlfn.IFS(Table1[[#This Row],[DEL]]="",0,Table1[[#This Row],[DEL]]="",0,ISBLANK(Table1[[#This Row],[PR APPR DATE]]),0,ISBLANK(Table1[[#This Row],[DEL]]),0,ISNONTEXT(Table1[[#This Row],[PR APPR DATE]]),Table1[[#This Row],[DEL]]-Table1[[#This Row],[PR APPR DATE]],Table1[[#This Row],[DEL]]="",0)} -> 0 | BQ4: =Table1[[#This Row],[ORG CHGS (AED)]]/3.673 -> 0 | BR4: =Table1[[#This Row],[FRT CHGS (AED)]]/3.673 -> 0 | BS4: =Table1[[#This Row],[DEST CHGS (AED)]]/3.673 -> 0 | BY4: =SUM(Table1[[#This Row],[ORG CHGS (AED)]],Table1[[#This Row],[FRT CHGS (AED)]],Table1[[#This Row],[DEST CHGS (AED)]]) -> 0 | BZ4: =SUM(Table1[[#This Row],[P2P VALUE]]+Table1[[#This Row],[Ancillary Charges (AED)]]) -> 0 | CD4: =IF(ISBLANK(Table1[[#This Row],[PR DATE]]),"Pending","Logged") -> Pending | CF4: =IF(ISBLANK(Table1[[#This Row],[SPO '#]]),"Pending","Received") -> Pending | CJ4: {=_xlfn.IFS(ISTEXT(Table1[[#This Row],[Invoice '#]]),"Billed",Table1[[#This Row],[PO STATUS]]="Received","Pending",Table1[[#This Row],[PO STATUS]]="Pending","Pending")} -> Pending | CM4: =IF(ISBLANK(Table1[[#This Row],[GRN]]),"Pending","Complete") -> Pending | CU4: =IF(Table1[[#This Row],[DEL]]="","",Table1[[#This Row],[REVISED ETD]]-Table1[[#This Row],[ETD]]) | CV4: =IF(Table1[[#This Row],[DEL]]="","",Table1[[#This Row],[REVISED ETA]]-Table1[[#This Row],[ETA]]) | CW4: =IF(Table1[[#This Row],[DEL]]="","",Table1[[#This Row],[ETA]]-Table1[[#This Row],[PO NEED BY DATE]]) | CX4: =Table1[[#This Row],[Invoice (AED)]]/3.673 -> 0 | CY4: {=_xlfn.IFS(Table1[[#This Row],[STATUS]]="Cancelled",,Table1[[#This Row],[STATUS]]="Pending",,Table1[[#This Row],[STATUS]]="Not Due",,ISNONTEXT(Table1[[#This Row],[CRD]]),Table1[[#This Row],[CRD]]-Table1[[#This Row],[PO NEED BY DATE]])} -> 0 | CZ4: =IF(Table1[[#This Row],[CRD]]<>"", Table1[[#This Row],[CRD]]-Table1[[#This Row],[PO CREATION DATE]], 0) -> 0 | DA4: =IF(Table1[[#This Row],[REVISED ETD]]<>"", Table1[[#This Row],[REVISED ETD]]-Table1[[#This Row],[CRD]], Table1[[#This Row],[ETD]]-Table1[[#This Row],[CRD]]) -> 0 | DB4: =IF(AND(Table1[[#This Row],[REVISED ETD]]<>"", Table1[[#This Row],[REVISED ETA]]<>""), Table1[[#This Row],[REVISED ETA]]-Table1[[#This Row],[REVISED ETD]], IF(AND(Table1[[#This Row],[REVISED ETA]]<>"", Table1[[#This Row],[REVISED ETD]]=""), Table1[[#This Row],[REVISED ETA]]-Table1[[#This Row],[ETD]], IF(AND(Table1[[#This Row],[REVISED ETA]]="", Table1[[#This Row],[REVISED ETD]]<>""), Table1[[#This Row],[ETA]]-Table1[[#This Row],[REVISED ETD]], IF(AND(Table1[[#This Row],[REVISED ETA]]="", Table1[[#This Row],[REVISED ETD]]=""), Table1[[#This Row],[ETA]]-Table1[[#This Row],[ETD]], "") ) ) ) -> 0 | DC4: =IF(Table1[[#This Row],[REVISED ETA]]<>"", Table1[[#This Row],[DEL]]-Table1[[#This Row],[REVISED ETA]], Table1[[#This Row],[DEL]]-Table1[[#This Row],[ETA]]) -> 0 | DD4: {=_xlfn.IFS(Table1[[#This Row],[STATUS]]="Cancelled",,Table1[[#This Row],[STATUS]]="Pending",,Table1[[#This Row],[STATUS]]="Not Due",,ISNONTEXT(Table1[[#This Row],[ETD]]),Table1[[#This Row],[ETA]]-Table1[[#This Row],[PO NEED BY DATE]])} -> 0 | DE4: =Table1[[#This Row],[PO NEED BY DATE]]-Table1[[#This Row],[DEL]] -> 45948 | DF4: =SUM(Table1[[#This Row],[CRD TO ETD]],Table1[[#This Row],[ETD TO ETA]],Table1[[#This Row],[ETA TO DEL]],Table1[[#This Row],[NBD TO ETA]],Table1[[#This Row],[NBD TO DEL]]) -> 45948
C5: STEP SOURCING TRADING L.L.C | D5: 422016887-19 | F5: cotton | G5: FC Cotton Coaster | AA5: 45945 | AB5: 45945 | AC5: 45945 | AD5: 45947 | AE5: 46119 | AO5: Not Due | AQ5: 478550 | BA5: =IF(Table1[[#This Row],[PO APPR DATE]]>0,IF(Table1[[#This Row],[PO APPR DATE]]-Table1[[#This Row],[PR APPR DATE]]<=5,1,1-ABS(Table1[[#This Row],[PO APPR DATE]]-Table1[[#This Row],[PR APPR DATE]])/5),0) -> 1 | BB5: {=IFERROR(_xlfn.IFS(ISBLANK(Table1[[#This Row],[PO APPR DATE]]),0,Table1[[#This Row],[CRD]]="",0,Table1[[#This Row],[CRD]]-Table1[[#This Row],[PO APPR DATE]]<=VLOOKUP(Table1[[#This Row],[Supplier ]],SupplierLeadTimeMaster!$A$2:$B$235,2,0),1,(Table1[[#This Row],[CRD]]-Table1[[#This Row],[PO APPR DATE]])>VLOOKUP(Table1[[#This Row],[Supplier ]],SupplierLeadTimeMaster!$A$2:$B$235,2,0),1-ABS(Table1[[#This Row],[CRD]]-Table1[[#This Row],[PO APPR DATE]])/VLOOKUP(Table1[[#This Row],[Supplier ]],SupplierLeadTimeMaster!$A$2:$B$235,2,0)),"")} -> 0 | BC5: =IFERROR(IF(AND(Table1[[#This Row],[ETD]]>0,Table1[[#This Row],[No of Days ISS Cont Booking LT]]>0),IF((Table1[[#This Row],[ETD]]-Table1[[#This Row],[CRD]])<=7,1,1-ABS(Table1[[#This Row],[ETD]]-Table1[[#This Row],[CRD]])/7),0),"") -> 0 | BD5: {=_xlfn.IFS(Table1[[#This Row],[DEL]]="",0,Table1[[#This Row],[ORG COUNTRY]]="",0,ISBLANK(Table1[[#This Row],[ETD]]),0,Table1[[#This Row],[ETA]]="",0,Table1[[#This Row],[ETA]]-Table1[[#This Row],[ETD]]<=VLOOKUP(Table1[[#This Row],[ORG COUNTRY]],CountryTransitTimeMaster!$B$2:$C$44,2,FALSE),1,Table1[[#This Row],[ETA]]-Table1[[#This Row],[ETD]]>VLOOKUP(Table1[[#This Row],[ORG COUNTRY]],CountryTransitTimeMaster!$B$2:$C$44,2,FALSE),1-ABS(Table1[[#This Row],[ETA]]-Table1[[#This Row],[ETD]])/VLOOKUP(Table1[[#This Row],[ORG COUNTRY]],CountryTransitTimeMaster!$B$2:$C$44,2,FALSE))} -> 0 | BE5: {=_xlfn.IFS(Table1[[#This Row],[DEL]]="",0,ISBLANK(Table1[[#This Row],[DEL]]),0,Table1[[#This Row],[DEL]]-Table1[[#This Row],[ETA]]<=3,1,(Table1[[#This Row],[DEL]]-Table1[[#This Row],[ETA]])>3,1-ABS(Table1[[#This Row],[DEL]]-Table1[[#This Row],[ETA]])/3)} -> 0 | BF5: =IFERROR(IF(Table1[[#This Row],[E2E Total LT]]>0,1-ABS(Table1[[#This Row],[E2E Total LT]]-Table1[[#This Row],[No of Days Total Comm LT (as per contract)]])/Table1[[#This Row],[No of Days Total Comm LT (as per contract)]],0),"") -> 0 | BG5: {=_xlfn.IFS(Table1[[#This Row],[DEL]]="",0,Table1[[#This Row],[STATUS]]="Cancelled",0,Table1[[#This Row],[ORG COUNTRY]]="",0,ISNONTEXT(Table1[[#This Row],[DEL]]),SUM(VLOOKUP(Table1[[#This Row],[Supplier ]],SupplierLeadTimeMaster!$A$2:$B$235,2,FALSE),VLOOKUP(Table1[[#This Row],[ORG COUNTRY]],CountryTransitTimeMaster!$B$2:$C$44,2,FALSE),7,3,5))} -> 0 | BH5: =IFERROR(IF(SUM(Table1[[#This Row],[No of Days Order Placement LT]],Table1[[#This Row],[No of Days Supplier Production Lead Time]],Table1[[#This Row],[No of Days Custom Clearance LT]],Table1[[#This Row],[No of Days ISS Cont Booking LT]],Table1[[#This Row],[No of Days Transit LT]])>500,0,SUM(Table1[[#This Row],[No of Days Order Placement LT]],Table1[[#This Row],[No of Days Supplier Production Lead Time]],Table1[[#This Row],[No of Days Custom Clearance LT]],Table1[[#This Row],[No of Days ISS Cont Booking LT]],Table1[[#This Row],[No of Days Transit LT]])),0) -> 0 | BI5: {=IFERROR(_xlfn.IFS((Table1[[#This Row],[No of Days Supplier Production Lead Time]])=" "," ",Table1[[#This Row],[Actual Lead (PO to Date)]]-Table1[[#This Row],[No of Days Total Comm LT (as per contract)]]<=15,"Healthy",Table1[[#This Row],[Actual Lead (PO to Date)]]-Table1[[#This Row],[No of Days Total Comm LT (as per contract)]]<=30,"Minor",Table1[[#This Row],[Actual Lead (PO to Date)]]-Table1[[#This Row],[No of Days Total Comm LT (as per contract)]]<=45,"Moderate",Table1[[#This Row],[Actual Lead (PO to Date)]]-Table1[[#This Row],[No of Days Total Comm LT (as per contract)]]<=60,"Major",Table1[[#This Row],[Actual Lead (PO to Date)]]-Table1[[#This Row],[No of Days Total Comm LT (as per contract)]]>60,"Severe",ISBLANK(Table1[[#This Row],[DEL]])," ",ISBLANK(Table1[[#This Row],[ETA]])," ",ISBLANK(Table1[[#This Row],[ETD]])," ",ISBLANK(Table1[[#This Row],[PR APPR DATE]])," ",ISBLANK(Table1[[#This Row],[Actual Lead (PO to Date)]])," ",ISBLANK(Table1[[#This Row],[No of Days Total Comm LT (as per contract)]])," ")," ")} -> Healthy | BJ5: {=IFERROR(_xlfn.IFS(Table1[[#This Row],[HEALTH CHECK]]=" ","",Table1[[#This Row],[HEALTH CHECK]]="Healthy"," ",Table1[[#This Row],[ON TIME ORDER PLACEMENT PERF %]]<100%,"PR to PO Delay",Table1[[#This Row],[Supplier committed product readiness performance % ]]<100%,"Product Readiness Delay",Table1[[#This Row],[ISS container booking performance %]]<100%,"Booking Delay",Table1[[#This Row],[ISS Transit Lead Time Perf %]]<100%,"Trans Shipment Delay",Table1[[#This Row],[ISS custom clearance Perf % ]]<100%,"Custom Clearance Delay")," ")} | BK5: {=_xlfn.IFS(ISBLANK(Table1[[#This Row],[PR APPR DATE]]),0,ISBLANK(Table1[[#This Row],[PO APPR DATE]]),0,ISNONTEXT(Table1[[#This Row],[PO APPR DATE]]),Table1[[#This Row],[PO APPR DATE]]-Table1[[#This Row],[PR APPR DATE]])} -> 0 | BL5: {=_xlfn.IFS((Table1[[#This Row],[DEL]])="",0,ISBLANK(Table1[[#This Row],[CRD]]),0,ISBLANK(Table1[[#This Row],[PO APPR DATE]]),0,ISNONTEXT(Table1[[#This Row],[PO APPR DATE]]),Table1[[#This Row],[CRD]]-Table1[[#This Row],[PO APPR DATE]])} -> 0 | BM5: =IFERROR(IF(Table1[[#This Row],[DEL]]>0,Table1[[#This Row],[DEL]]-Table1[[#This Row],[ETA]],0),0) -> 0 | BN5: =IFERROR(IF(Table1[[#This Row],[ETD]]>0,(Table1[[#This Row],[ETD]]-Table1[[#This Row],[CRD]]),0),"") -> 0 | BO5: =IFERROR(IF(Table1[[#This Row],[ETA]]>0,(Table1[[#This Row],[ETA]]-Table1[[#This Row],[ETD]]),0),0) -> 0 | BP5: {=_xlfn.IFS(Table1[[#This Row],[DEL]]="",0,Table1[[#This Row],[DEL]]="",0,ISBLANK(Table1[[#This Row],[PR APPR DATE]]),0,ISBLANK(Table1[[#This Row],[DEL]]),0,ISNONTEXT(Table1[[#This Row],[PR APPR DATE]]),Table1[[#This Row],[DEL]]-Table1[[#This Row],[PR APPR DATE]],Table1[[#This Row],[DEL]]="",0)} -> 0 | BQ5: =Table1[[#This Row],[ORG CHGS (AED)]]/3.673 -> 0 | BR5: =Table1[[#This Row],[FRT CHGS (AED)]]/3.673 -> 0 | BS5: =Table1[[#This Row],[DEST CHGS (AED)]]/3.673 -> 0 | BY5: =SUM(Table1[[#This Row],[ORG CHGS (AED)]],Table1[[#This Row],[FRT CHGS (AED)]],Table1[[#This Row],[DEST CHGS (AED)]]) -> 0 | BZ5: =SUM(Table1[[#This Row],[P2P VALUE]]+Table1[[#This Row],[Ancillary Charges (AED)]]) -> 0 | CD5: =IF(ISBLANK(Table1[[#This Row],[PR DATE]]),"Pending","Logged") -> Pending | CF5: =IF(ISBLANK(Table1[[#This Row],[SPO '#]]),"Pending","Received") -> Pending | CJ5: {=_xlfn.IFS(ISTEXT(Table1[[#This Row],[Invoice '#]]),"Billed",Table1[[#This Row],[PO STATUS]]="Received","Pending",Table1[[#This Row],[PO STATUS]]="Pending","Pending")} -> Pending | CM5: =IF(ISBLANK(Table1[[#This Row],[GRN]]),"Pending","Complete") -> Pending | CU5: =IF(Table1[[#This Row],[DEL]]="","",Table1[[#This Row],[REVISED ETD]]-Table1[[#This Row],[ETD]]) | CV5: =IF(Table1[[#This Row],[DEL]]="","",Table1[[#This Row],[REVISED ETA]]-Table1[[#This Row],[ETA]]) | CW5: =IF(Table1[[#This Row],[DEL]]="","",Table1[[#This Row],[ETA]]-Table1[[#This Row],[PO NEED BY DATE]]) | CX5: =Table1[[#This Row],[Invoice (AED)]]/3.673 -> 0 | CY5: {=_xlfn.IFS(Table1[[#This Row],[STATUS]]="Cancelled",,Table1[[#This Row],[STATUS]]="Pending",,Table1[[#This Row],[STATUS]]="Not Due",,ISNONTEXT(Table1[[#This Row],[CRD]]),Table1[[#This Row],[CRD]]-Table1[[#This Row],[PO NEED BY DATE]])} -> 0 | CZ5: =IF(Table1[[#This Row],[CRD]]<>"", Table1[[#This Row],[CRD]]-Table1[[#This Row],[PO CREATION DATE]], 0) -> 0 | DA5: =IF(Table1[[#This Row],[REVISED ETD]]<>"", Table1[[#This Row],[REVISED ETD]]-Table1[[#This Row],[CRD]], Table1[[#This Row],[ETD]]-Table1[[#This Row],[CRD]]) -> 0 | DB5: =IF(AND(Table1[[#This Row],[REVISED ETD]]<>"", Table1[[#This Row],[REVISED ETA]]<>""), Table1[[#This Row],[REVISED ETA]]-Table1[[#This Row],[REVISED ETD]], IF(AND(Table1[[#This Row],[REVISED ETA]]<>"", Table1[[#This Row],[REVISED ETD]]=""), Table1[[#This Row],[REVISED ETA]]-Table1[[#This Row],[ETD]], IF(AND(Table1[[#This Row],[REVISED ETA]]="", Table1[[#This Row],[REVISED ETD]]<>""), Table1[[#This Row],[ETA]]-Table1[[#This Row],[REVISED ETD]], IF(AND(Table1[[#This Row],[REVISED ETA]]="", Table1[[#This Row],[REVISED ETD]]=""), Table1[[#This Row],[ETA]]-Table1[[#This Row],[ETD]], "") ) ) ) -> 0 | DC5: =IF(Table1[[#This Row],[REVISED ETA]]<>"", Table1[[#This Row],[DEL]]-Table1[[#This Row],[REVISED ETA]], Table1[[#This Row],[DEL]]-Table1[[#This Row],[ETA]]) -> 0 | DD5: {=_xlfn.IFS(Table1[[#This Row],[STATUS]]="Cancelled",,Table1[[#This Row],[STATUS]]="Pending",,Table1[[#This Row],[STATUS]]="Not Due",,ISNONTEXT(Table1[[#This Row],[ETD]]),Table1[[#This Row],[ETA]]-Table1[[#This Row],[PO NEED BY DATE]])} -> 0 | DE5: =Table1[[#This Row],[PO NEED BY DATE]]-Table1[[#This Row],[DEL]] -> 46119 | DF5: =SUM(Table1[[#This Row],[CRD TO ETD]],Table1[[#This Row],[ETD TO ETA]],Table1[[#This Row],[ETA TO DEL]],Table1[[#This Row],[NBD TO ETA]],Table1[[#This Row],[NBD TO DEL]]) -> 46119
C6: STEP SOURCING TRADING L.L.C | D6: 422016887-19 | F6: fc cotton | G6: FC Cotton Coaster | AA6: 45945 | AB6: 45945 | AC6: 45945 | AD6: 45947 | AE6: 46057 | AO6: Pending | AQ6: 479000 | BA6: =IF(Table1[[#This Row],[PO APPR DATE]]>0,IF(Table1[[#This Row],[PO APPR DATE]]-Table1[[#This Row],[PR APPR DATE]]<=5,1,1-ABS(Table1[[#This Row],[PO APPR DATE]]-Table1[[#This Row],[PR APPR DATE]])/5),0) -> 1 | BB6: {=IFERROR(_xlfn.IFS(ISBLANK(Table1[[#This Row],[PO APPR DATE]]),0,Table1[[#This Row],[CRD]]="",0,Table1[[#This Row],[CRD]]-Table1[[#This Row],[PO APPR DATE]]<=VLOOKUP(Table1[[#This Row],[Supplier ]],SupplierLeadTimeMaster!$A$2:$B$235,2,0),1,(Table1[[#This Row],[CRD]]-Table1[[#This Row],[PO APPR DATE]])>VLOOKUP(Table1[[#This Row],[Supplier ]],SupplierLeadTimeMaster!$A$2:$B$235,2,0),1-ABS(Table1[[#This Row],[CRD]]-Table1[[#This Row],[PO APPR DATE]])/VLOOKUP(Table1[[#This Row],[Supplier ]],SupplierLeadTimeMaster!$A$2:$B$235,2,0)),"")} -> 0 | BC6: =IFERROR(IF(AND(Table1[[#This Row],[ETD]]>0,Table1[[#This Row],[No of Days ISS Cont Booking LT]]>0),IF((Table1[[#This Row],[ETD]]-Table1[[#This Row],[CRD]])<=7,1,1-ABS(Table1[[#This Row],[ETD]]-Table1[[#This Row],[CRD]])/7),0),"") -> 0 | BD6: {=_xlfn.IFS(Table1[[#This Row],[DEL]]="",0,Table1[[#This Row],[ORG COUNTRY]]="",0,ISBLANK(Table1[[#This Row],[ETD]]),0,Table1[[#This Row],[ETA]]="",0,Table1[[#This Row],[ETA]]-Table1[[#This Row],[ETD]]<=VLOOKUP(Table1[[#This Row],[ORG COUNTRY]],CountryTransitTimeMaster!$B$2:$C$44,2,FALSE),1,Table1[[#This Row],[ETA]]-Table1[[#This Row],[ETD]]>VLOOKUP(Table1[[#This Row],[ORG COUNTRY]],CountryTransitTimeMaster!$B$2:$C$44,2,FALSE),1-ABS(Table1[[#This Row],[ETA]]-Table1[[#This Row],[ETD]])/VLOOKUP(Table1[[#This Row],[ORG COUNTRY]],CountryTransitTimeMaster!$B$2:$C$44,2,FALSE))} -> 0 | BE6: {=_xlfn.IFS(Table1[[#This Row],[DEL]]="",0,ISBLANK(Table1[[#This Row],[DEL]]),0,Table1[[#This Row],[DEL]]-Table1[[#This Row],[ETA]]<=3,1,(Table1[[#This Row],[DEL]]-Table1[[#This Row],[ETA]])>3,1-ABS(Table1[[#This Row],[DEL]]-Table1[[#This Row],[ETA]])/3)} -> 0 | BF6: =IFERROR(IF(Table1[[#This Row],[E2E Total LT]]>0,1-ABS(Table1[[#This Row],[E2E Total LT]]-Table1[[#This Row],[No of Days Total Comm LT (as per contract)]])/Table1[[#This Row],[No of Days Total Comm LT (as per contract)]],0),"") -> 0 | BG6: {=_xlfn.IFS(Table1[[#This Row],[DEL]]="",0,Table1[[#This Row],[STATUS]]="Cancelled",0,Table1[[#This Row],[ORG COUNTRY]]="",0,ISNONTEXT(Table1[[#This Row],[DEL]]),SUM(VLOOKUP(Table1[[#This Row],[Supplier ]],SupplierLeadTimeMaster!$A$2:$B$235,2,FALSE),VLOOKUP(Table1[[#This Row],[ORG COUNTRY]],CountryTransitTimeMaster!$B$2:$C$44,2,FALSE),7,3,5))} -> 0 | BH6: =IFERROR(IF(SUM(Table1[[#This Row],[No of Days Order Placement LT]],Table1[[#This Row],[No of Days Supplier Production Lead Time]],Table1[[#This Row],[No of Days Custom Clearance LT]],Table1[[#This Row],[No of Days ISS Cont Booking LT]],Table1[[#This Row],[No of Days Transit LT]])>500,0,SUM(Table1[[#This Row],[No of Days Order Placement LT]],Table1[[#This Row],[No of Days Supplier Production Lead Time]],Table1[[#This Row],[No of Days Custom Clearance LT]],Table1[[#This Row],[No of Days ISS Cont Booking LT]],Table1[[#This Row],[No of Days Transit LT]])),0) -> 0 | BI6: {=IFERROR(_xlfn.IFS((Table1[[#This Row],[No of Days Supplier Production Lead Time]])=" "," ",Table1[[#This Row],[Actual Lead (PO to Date)]]-Table1[[#This Row],[No of Days Total Comm LT (as per contract)]]<=15,"Healthy",Table1[[#This Row],[Actual Lead (PO to Date)]]-Table1[[#This Row],[No of Days Total Comm LT (as per contract)]]<=30,"Minor",Table1[[#This Row],[Actual Lead (PO to Date)]]-Table1[[#This Row],[No of Days Total Comm LT (as per contract)]]<=45,"Moderate",Table1[[#This Row],[Actual Lead (PO to Date)]]-Table1[[#This Row],[No of Days Total Comm LT (as per contract)]]<=60,"Major",Table1[[#This Row],[Actual Lead (PO to Date)]]-Table1[[#This Row],[No of Days Total Comm LT (as per contract)]]>60,"Severe",ISBLANK(Table1[[#This Row],[DEL]])," ",ISBLANK(Table1[[#This Row],[ETA]])," ",ISBLANK(Table1[[#This Row],[ETD]])," ",ISBLANK(Table1[[#This Row],[PR APPR DATE]])," ",ISBLANK(Table1[[#This Row],[Actual Lead (PO to Date)]])," ",ISBLANK(Table1[[#This Row],[No of Days Total Comm LT (as per contract)]])," ")," ")} -> Healthy | BJ6: {=IFERROR(_xlfn.IFS(Table1[[#This Row],[HEALTH CHECK]]=" ","",Table1[[#This Row],[HEALTH CHECK]]="Healthy"," ",Table1[[#This Row],[ON TIME ORDER PLACEMENT PERF %]]<100%,"PR to PO Delay",Table1[[#This Row],[Supplier committed product readiness performance % ]]<100%,"Product Readiness Delay",Table1[[#This Row],[ISS container booking performance %]]<100%,"Booking Delay",Table1[[#This Row],[ISS Transit Lead Time Perf %]]<100%,"Trans Shipment Delay",Table1[[#This Row],[ISS custom clearance Perf % ]]<100%,"Custom Clearance Delay")," ")} | BK6: {=_xlfn.IFS(ISBLANK(Table1[[#This Row],[PR APPR DATE]]),0,ISBLANK(Table1[[#This Row],[PO APPR DATE]]),0,ISNONTEXT(Table1[[#This Row],[PO APPR DATE]]),Table1[[#This Row],[PO APPR DATE]]-Table1[[#This Row],[PR APPR DATE]])} -> 0 | BL6: {=_xlfn.IFS((Table1[[#This Row],[DEL]])="",0,ISBLANK(Table1[[#This Row],[CRD]]),0,ISBLANK(Table1[[#This Row],[PO APPR DATE]]),0,ISNONTEXT(Table1[[#This Row],[PO APPR DATE]]),Table1[[#This Row],[CRD]]-Table1[[#This Row],[PO APPR DATE]])} -> 0 | BM6: =IFERROR(IF(Table1[[#This Row],[DEL]]>0,Table1[[#This Row],[DEL]]-Table1[[#This Row],[ETA]],0),0) -> 0 | BN6: =IFERROR(IF(Table1[[#This Row],[ETD]]>0,(Table1[[#This Row],[ETD]]-Table1[[#This Row],[CRD]]),0),"") -> 0 | BO6: =IFERROR(IF(Table1[[#This Row],[ETA]]>0,(Table1[[#This Row],[ETA]]-Table1[[#This Row],[ETD]]),0),0) -> 0 | BP6: {=_xlfn.IFS(Table1[[#This Row],[DEL]]="",0,Table1[[#This Row],[DEL]]="",0,ISBLANK(Table1[[#This Row],[PR APPR DATE]]),0,ISBLANK(Table1[[#This Row],[DEL]]),0,ISNONTEXT(Table1[[#This Row],[PR APPR DATE]]),Table1[[#This Row],[DEL]]-Table1[[#This Row],[PR APPR DATE]],Table1[[#This Row],[DEL]]="",0)} -> 0 | BQ6: =Table1[[#This Row],[ORG CHGS (AED)]]/3.673 -> 0 | BR6: =Table1[[#This Row],[FRT CHGS (AED)]]/3.673 -> 0 | BS6: =Table1[[#This Row],[DEST CHGS (AED)]]/3.673 -> 0 | BY6: =SUM(Table1[[#This Row],[ORG CHGS (AED)]],Table1[[#This Row],[FRT CHGS (AED)]],Table1[[#This Row],[DEST CHGS (AED)]]) -> 0 | BZ6: =SUM(Table1[[#This Row],[P2P VALUE]]+Table1[[#This Row],[Ancillary Charges (AED)]]) -> 0 | CD6: =IF(ISBLANK(Table1[[#This Row],[PR DATE]]),"Pending","Logged") -> Pending | CF6: =IF(ISBLANK(Table1[[#This Row],[SPO '#]]),"Pending","Received") -> Pending | CJ6: {=_xlfn.IFS(ISTEXT(Table1[[#This Row],[Invoice '#]]),"Billed",Table1[[#This Row],[PO STATUS]]="Received","Pending",Table1[[#This Row],[PO STATUS]]="Pending","Pending")} -> Pending | CM6: =IF(ISBLANK(Table1[[#This Row],[GRN]]),"Pending","Complete") -> Pending | CU6: =IF(Table1[[#This Row],[DEL]]="","",Table1[[#This Row],[REVISED ETD]]-Table1[[#This Row],[ETD]]) | CV6: =IF(Table1[[#This Row],[DEL]]="","",Table1[[#This Row],[REVISED ETA]]-Table1[[#This Row],[ETA]]) | CW6: =IF(Table1[[#This Row],[DEL]]="","",Table1[[#This Row],[ETA]]-Table1[[#This Row],[PO NEED BY DATE]]) | CX6: =Table1[[#This Row],[Invoice (AED)]]/3.673 -> 0 | CY6: {=_xlfn.IFS(Table1[[#This Row],[STATUS]]="Cancelled",,Table1[[#This Row],[STATUS]]="Pending",,Table1[[#This Row],[STATUS]]="Not Due",,ISNONTEXT(Table1[[#This Row],[CRD]]),Table1[[#This Row],[CRD]]-Table1[[#This Row],[PO NEED BY DATE]])} -> 0 | CZ6: =IF(Table1[[#This Row],[CRD]]<>"", Table1[[#This Row],[CRD]]-Table1[[#This Row],[PO CREATION DATE]], 0) -> 0 | DA6: =IF(Table1[[#This Row],[REVISED ETD]]<>"", Table1[[#This Row],[REVISED ETD]]-Table1[[#This Row],[CRD]], Table1[[#This Row],[ETD]]-Table1[[#This Row],[CRD]]) -> 0 | DB6: =IF(AND(Table1[[#This Row],[REVISED ETD]]<>"", Table1[[#This Row],[REVISED ETA]]<>""), Table1[[#This Row],[REVISED ETA]]-Table1[[#This Row],[REVISED ETD]], IF(AND(Table1[[#This Row],[REVISED ETA]]<>"", Table1[[#This Row],[REVISED ETD]]=""), Table1[[#This Row],[REVISED ETA]]-Table1[[#This Row],[ETD]], IF(AND(Table1[[#This Row],[REVISED ETA]]="", Table1[[#This Row],[REVISED ETD]]<>""), Table1[[#This Row],[ETA]]-Table1[[#This Row],[REVISED ETD]], IF(AND(Table1[[#This Row],[REVISED ETA]]="", Table1[[#This Row],[REVISED ETD]]=""), Table1[[#This Row],[ETA]]-Table1[[#This Row],[ETD]], "") ) ) ) -> 0 | DC6: =IF(Table1[[#This Row],[REVISED ETA]]<>"", Table1[[#This Row],[DEL]]-Table1[[#This Row],[REVISED ETA]], Table1[[#This Row],[DEL]]-Table1[[#This Row],[ETA]]) -> 0 | DD6: {=_xlfn.IFS(Table1[[#This Row],[STATUS]]="Cancelled",,Table1[[#This Row],[STATUS]]="Pending",,Table1[[#This Row],[STATUS]]="Not Due",,ISNONTEXT(Table1[[#This Row],[ETD]]),Table1[[#This Row],[ETA]]-Table1[[#This Row],[PO NEED BY DATE]])} -> 0 | DE6: =Table1[[#This Row],[PO NEED BY DATE]]-Table1[[#This Row],[DEL]] -> 46057 | DF6: =SUM(Table1[[#This Row],[CRD TO ETD]],Table1[[#This Row],[ETD TO ETA]],Table1[[#This Row],[ETA TO DEL]],Table1[[#This Row],[NBD TO ETA]],Table1[[#This Row],[NBD TO DEL]]) -> 46057
C7: STEP SOURCING TRADING L.L.C | D7: 422016887-19 | F7: fc coaster | G7: FC Cotton Coaster | AA7: 45945 | AB7: 45945 | AC7: 45945 | AD7: 45947 | AE7: 46042 | AO7: Pending | AQ7: 480000 | BA7: =IF(Table1[[#This Row],[PO APPR DATE]]>0,IF(Table1[[#This Row],[PO APPR DATE]]-Table1[[#This Row],[PR APPR DATE]]<=5,1,1-ABS(Table1[[#This Row],[PO APPR DATE]]-Table1[[#This Row],[PR APPR DATE]])/5),0) -> 1 | BB7: {=IFERROR(_xlfn.IFS(ISBLANK(Table1[[#This Row],[PO APPR DATE]]),0,Table1[[#This Row],[CRD]]="",0,Table1[[#This Row],[CRD]]-Table1[[#This Row],[PO APPR DATE]]<=VLOOKUP(Table1[[#This Row],[Supplier ]],SupplierLeadTimeMaster!$A$2:$B$235,2,0),1,(Table1[[#This Row],[CRD]]-Table1[[#This Row],[PO APPR DATE]])>VLOOKUP(Table1[[#This Row],[Supplier ]],SupplierLeadTimeMaster!$A$2:$B$235,2,0),1-ABS(Table1[[#This Row],[CRD]]-Table1[[#This Row],[PO APPR DATE]])/VLOOKUP(Table1[[#This Row],[Supplier ]],SupplierLeadTimeMaster!$A$2:$B$235,2,0)),"")} -> 0 | BC7: =IFERROR(IF(AND(Table1[[#This Row],[ETD]]>0,Table1[[#This Row],[No of Days ISS Cont Booking LT]]>0),IF((Table1[[#This Row],[ETD]]-Table1[[#This Row],[CRD]])<=7,1,1-ABS(Table1[[#This Row],[ETD]]-Table1[[#This Row],[CRD]])/7),0),"") -> 0 | BD7: {=_xlfn.IFS(Table1[[#This Row],[DEL]]="",0,Table1[[#This Row],[ORG COUNTRY]]="",0,ISBLANK(Table1[[#This Row],[ETD]]),0,Table1[[#This Row],[ETA]]="",0,Table1[[#This Row],[ETA]]-Table1[[#This Row],[ETD]]<=VLOOKUP(Table1[[#This Row],[ORG COUNTRY]],CountryTransitTimeMaster!$B$2:$C$44,2,FALSE),1,Table1[[#This Row],[ETA]]-Table1[[#This Row],[ETD]]>VLOOKUP(Table1[[#This Row],[ORG COUNTRY]],CountryTransitTimeMaster!$B$2:$C$44,2,FALSE),1-ABS(Table1[[#This Row],[ETA]]-Table1[[#This Row],[ETD]])/VLOOKUP(Table1[[#This Row],[ORG COUNTRY]],CountryTransitTimeMaster!$B$2:$C$44,2,FALSE))} -> 0 | BE7: {=_xlfn.IFS(Table1[[#This Row],[DEL]]="",0,ISBLANK(Table1[[#This Row],[DEL]]),0,Table1[[#This Row],[DEL]]-Table1[[#This Row],[ETA]]<=3,1,(Table1[[#This Row],[DEL]]-Table1[[#This Row],[ETA]])>3,1-ABS(Table1[[#This Row],[DEL]]-Table1[[#This Row],[ETA]])/3)} -> 0 | BF7: =IFERROR(IF(Table1[[#This Row],[E2E Total LT]]>0,1-ABS(Table1[[#This Row],[E2E Total LT]]-Table1[[#This Row],[No of Days Total Comm LT (as per contract)]])/Table1[[#This Row],[No of Days Total Comm LT (as per contract)]],0),"") -> 0 | BG7: {=_xlfn.IFS(Table1[[#This Row],[DEL]]="",0,Table1[[#This Row],[STATUS]]="Cancelled",0,Table1[[#This Row],[ORG COUNTRY]]="",0,ISNONTEXT(Table1[[#This Row],[DEL]]),SUM(VLOOKUP(Table1[[#This Row],[Supplier ]],SupplierLeadTimeMaster!$A$2:$B$235,2,FALSE),VLOOKUP(Table1[[#This Row],[ORG COUNTRY]],CountryTransitTimeMaster!$B$2:$C$44,2,FALSE),7,3,5))} -> 0 | BH7: =IFERROR(IF(SUM(Table1[[#This Row],[No of Days Order Placement LT]],Table1[[#This Row],[No of Days Supplier Production Lead Time]],Table1[[#This Row],[No of Days Custom Clearance LT]],Table1[[#This Row],[No of Days ISS Cont Booking LT]],Table1[[#This Row],[No of Days Transit LT]])>500,0,SUM(Table1[[#This Row],[No of Days Order Placement LT]],Table1[[#This Row],[No of Days Supplier Production Lead Time]],Table1[[#This Row],[No of Days Custom Clearance LT]],Table1[[#This Row],[No of Days ISS Cont Booking LT]],Table1[[#This Row],[No of Days Transit LT]])),0) -> 0 | BI7: {=IFERROR(_xlfn.IFS((Table1[[#This Row],[No of Days Supplier Production Lead Time]])=" "," ",Table1[[#This Row],[Actual Lead (PO to Date)]]-Table1[[#This Row],[No of Days Total Comm LT (as per contract)]]<=15,"Healthy",Table1[[#This Row],[Actual Lead (PO to Date)]]-Table1[[#This Row],[No of Days Total Comm LT (as per contract)]]<=30,"Minor",Table1[[#This Row],[Actual Lead (PO to Date)]]-Table1[[#This Row],[No of Days Total Comm LT (as per contract)]]<=45,"Moderate",Table1[[#This Row],[Actual Lead (PO to Date)]]-Table1[[#This Row],[No of Days Total Comm LT (as per contract)]]<=60,"Major",Table1[[#This Row],[Actual Lead (PO to Date)]]-Table1[[#This Row],[No of Days Total Comm LT (as per contract)]]>60,"Severe",ISBLANK(Table1[[#This Row],[DEL]])," ",ISBLANK(Table1[[#This Row],[ETA]])," ",ISBLANK(Table1[[#This Row],[ETD]])," ",ISBLANK(Table1[[#This Row],[PR APPR DATE]])," ",ISBLANK(Table1[[#This Row],[Actual Lead (PO to Date)]])," ",ISBLANK(Table1[[#This Row],[No of Days Total Comm LT (as per contract)]])," ")," ")} -> Healthy | BJ7: {=IFERROR(_xlfn.IFS(Table1[[#This Row],[HEALTH CHECK]]=" ","",Table1[[#This Row],[HEALTH CHECK]]="Healthy"," ",Table1[[#This Row],[ON TIME ORDER PLACEMENT PERF %]]<100%,"PR to PO Delay",Table1[[#This Row],[Supplier committed product readiness performance % ]]<100%,"Product Readiness Delay",Table1[[#This Row],[ISS container booking performance %]]<100%,"Booking Delay",Table1[[#This Row],[ISS Transit Lead Time Perf %]]<100%,"Trans Shipment Delay",Table1[[#This Row],[ISS custom clearance Perf % ]]<100%,"Custom Clearance Delay")," ")} | BK7: {=_xlfn.IFS(ISBLANK(Table1[[#This Row],[PR APPR DATE]]),0,ISBLANK(Table1[[#This Row],[PO APPR DATE]]),0,ISNONTEXT(Table1[[#This Row],[PO APPR DATE]]),Table1[[#This Row],[PO APPR DATE]]-Table1[[#This Row],[PR APPR DATE]])} -> 0 | BL7: {=_xlfn.IFS((Table1[[#This Row],[DEL]])="",0,ISBLANK(Table1[[#This Row],[CRD]]),0,ISBLANK(Table1[[#This Row],[PO APPR DATE]]),0,ISNONTEXT(Table1[[#This Row],[PO APPR DATE]]),Table1[[#This Row],[CRD]]-Table1[[#This Row],[PO APPR DATE]])} -> 0 | BM7: =IFERROR(IF(Table1[[#This Row],[DEL]]>0,Table1[[#This Row],[DEL]]-Table1[[#This Row],[ETA]],0),0) -> 0 | BN7: =IFERROR(IF(Table1[[#This Row],[ETD]]>0,(Table1[[#This Row],[ETD]]-Table1[[#This Row],[CRD]]),0),"") -> 0 | BO7: =IFERROR(IF(Table1[[#This Row],[ETA]]>0,(Table1[[#This Row],[ETA]]-Table1[[#This Row],[ETD]]),0),0) -> 0 | BP7: {=_xlfn.IFS(Table1[[#This Row],[DEL]]="",0,Table1[[#This Row],[DEL]]="",0,ISBLANK(Table1[[#This Row],[PR APPR DATE]]),0,ISBLANK(Table1[[#This Row],[DEL]]),0,ISNONTEXT(Table1[[#This Row],[PR APPR DATE]]),Table1[[#This Row],[DEL]]-Table1[[#This Row],[PR APPR DATE]],Table1[[#This Row],[DEL]]="",0)} -> 0 | BQ7: =Table1[[#This Row],[ORG CHGS (AED)]]/3.673 -> 0 | BR7: =Table1[[#This Row],[FRT CHGS (AED)]]/3.673 -> 0 | BS7: =Table1[[#This Row],[DEST CHGS (AED)]]/3.673 -> 0 | BY7: =SUM(Table1[[#This Row],[ORG CHGS (AED)]],Table1[[#This Row],[FRT CHGS (AED)]],Table1[[#This Row],[DEST CHGS (AED)]]) -> 0 | BZ7: =SUM(Table1[[#This Row],[P2P VALUE]]+Table1[[#This Row],[Ancillary Charges (AED)]]) -> 0 | CD7: =IF(ISBLANK(Table1[[#This Row],[PR DATE]]),"Pending","Logged") -> Pending | CF7: =IF(ISBLANK(Table1[[#This Row],[SPO '#]]),"Pending","Received") -> Pending | CJ7: {=_xlfn.IFS(ISTEXT(Table1[[#This Row],[Invoice '#]]),"Billed",Table1[[#This Row],[PO STATUS]]="Received","Pending",Table1[[#This Row],[PO STATUS]]="Pending","Pending")} -> Pending | CM7: =IF(ISBLANK(Table1[[#This Row],[GRN]]),"Pending","Complete") -> Pending | CU7: =IF(Table1[[#This Row],[DEL]]="","",Table1[[#This Row],[REVISED ETD]]-Table1[[#This Row],[ETD]]) | CV7: =IF(Table1[[#This Row],[DEL]]="","",Table1[[#This Row],[REVISED ETA]]-Table1[[#This Row],[ETA]]) | CW7: =IF(Table1[[#This Row],[DEL]]="","",Table1[[#This Row],[ETA]]-Table1[[#This Row],[PO NEED BY DATE]]) | CX7: =Table1[[#This Row],[Invoice (AED)]]/3.673 -> 0 | CY7: {=_xlfn.IFS(Table1[[#This Row],[STATUS]]="Cancelled",,Table1[[#This Row],[STATUS]]="Pending",,Table1[[#This Row],[STATUS]]="Not Due",,ISNONTEXT(Table1[[#This Row],[CRD]]),Table1[[#This Row],[CRD]]-Table1[[#This Row],[PO NEED BY DATE]])} -> 0 | CZ7: =IF(Table1[[#This Row],[CRD]]<>"", Table1[[#This Row],[CRD]]-Table1[[#This Row],[PO CREATION DATE]], 0) -> 0 | DA7: =IF(Table1[[#This Row],[REVISED ETD]]<>"", Table1[[#This Row],[REVISED ETD]]-Table1[[#This Row],[CRD]], Table1[[#This Row],[ETD]]-Table1[[#This Row],[CRD]]) -> 0 | DB7: =IF(AND(Table1[[#This Row],[REVISED ETD]]<>"", Table1[[#This Row],[REVISED ETA]]<>""), Table1[[#This Row],[REVISED ETA]]-Table1[[#This Row],[REVISED ETD]], IF(AND(Table1[[#This Row],[REVISED ETA]]<>"", Table1[[#This Row],[REVISED ETD]]=""), Table1[[#This Row],[REVISED ETA]]-Table1[[#This Row],[ETD]], IF(AND(Table1[[#This Row],[REVISED ETA]]="", Table1[[#This Row],[REVISED ETD]]<>""), Table1[[#This Row],[ETA]]-Table1[[#This Row],[REVISED ETD]], IF(AND(Table1[[#This Row],[REVISED ETA]]="", Table1[[#This Row],[REVISED ETD]]=""), Table1[[#This Row],[ETA]]-Table1[[#This Row],[ETD]], "") ) ) ) -> 0 | DC7: =IF(Table1[[#This Row],[REVISED ETA]]<>"", Table1[[#This Row],[DEL]]-Table1[[#This Row],[REVISED ETA]], Table1[[#This Row],[DEL]]-Table1[[#This Row],[ETA]]) -> 0 | DD7: {=_xlfn.IFS(Table1[[#This Row],[STATUS]]="Cancelled",,Table1[[#This Row],[STATUS]]="Pending",,Table1[[#This Row],[STATUS]]="Not Due",,ISNONTEXT(Table1[[#This Row],[ETD]]),Table1[[#This Row],[ETA]]-Table1[[#This Row],[PO NEED BY DATE]])} -> 0 | DE7: =Table1[[#This Row],[PO NEED BY DATE]]-Table1[[#This Row],[DEL]] -> 46042 | DF7: =SUM(Table1[[#This Row],[CRD TO ETD]],Table1[[#This Row],[ETD TO ETA]],Table1[[#This Row],[ETA TO DEL]],Table1[[#This Row],[NBD TO ETA]],Table1[[#This Row],[NBD TO DEL]]) -> 46042
C8: IACOBUCCI HF AEROSPACE S.P.A.,STEP SOURCING TRADING L.L.C | D8: 422007642-17 | E8: 422016887-19 | F8: PO should be fulfilled|cotton|fc cotton | G8: STEAM SPOUT|FC Cotton Coaster | H8: EM000128 | AA8: 45945 | AB8: 45945 | AC8: 45945 | AD8: 45947 | AE8: 46021 | AO8: On Going | AQ8: 422007642-17-100|422016887-19-1250 | BA8: =IF(Table1[[#This Row],[PO APPR DATE]]>0,IF(Table1[[#This Row],[PO APPR DATE]]-Table1[[#This Row],[PR APPR DATE]]<=5,1,1-ABS(Table1[[#This Row],[PO APPR DATE]]-Table1[[#This Row],[PR APPR DATE]])/5),0) -> 1 | BB8: {=IFERROR(_xlfn.IFS(ISBLANK(Table1[[#This Row],[PO APPR DATE]]),0,Table1[[#This Row],[CRD]]="",0,Table1[[#This Row],[CRD]]-Table1[[#This Row],[PO APPR DATE]]<=VLOOKUP(Table1[[#This Row],[Supplier ]],SupplierLeadTimeMaster!$A$2:$B$235,2,0),1,(Table1[[#This Row],[CRD]]-Table1[[#This Row],[PO APPR DATE]])>VLOOKUP(Table1[[#This Row],[Supplier ]],SupplierLeadTimeMaster!$A$2:$B$235,2,0),1-ABS(Table1[[#This Row],[CRD]]-Table1[[#This Row],[PO APPR DATE]])/VLOOKUP(Table1[[#This Row],[Supplier ]],SupplierLeadTimeMaster!$A$2:$B$235,2,0)),"")} -> 0 | BC8: =IFERROR(IF(AND(Table1[[#This Row],[ETD]]>0,Table1[[#This Row],[No of Days ISS Cont Booking LT]]>0),IF((Table1[[#This Row],[ETD]]-Table1[[#This Row],[CRD]])<=7,1,1-ABS(Table1[[#This Row],[ETD]]-Table1[[#This Row],[CRD]])/7),0),"") -> 0 | BD8: {=_xlfn.IFS(Table1[[#This Row],[DEL]]="",0,Table1[[#This Row],[ORG COUNTRY]]="",0,ISBLANK(Table1[[#This Row],[ETD]]),0,Table1[[#This Row],[ETA]]="",0,Table1[[#This Row],[ETA]]-Table1[[#This Row],[ETD]]<=VLOOKUP(Table1[[#This Row],[ORG COUNTRY]],CountryTransitTimeMaster!$B$2:$C$44,2,FALSE),1,Table1[[#This Row],[ETA]]-Table1[[#This Row],[ETD]]>VLOOKUP(Table1[[#This Row],[ORG COUNTRY]],CountryTransitTimeMaster!$B$2:$C$44,2,FALSE),1-ABS(Table1[[#This Row],[ETA]]-Table1[[#This Row],[ETD]])/VLOOKUP(Table1[[#This Row],[ORG COUNTRY]],CountryTransitTimeMaster!$B$2:$C$44,2,FALSE))} -> 0 | BE8: {=_xlfn.IFS(Table1[[#This Row],[DEL]]="",0,ISBLANK(Table1[[#This Row],[DEL]]),0,Table1[[#This Row],[DEL]]-Table1[[#This Row],[ETA]]<=3,1,(Table1[[#This Row],[DEL]]-Table1[[#This Row],[ETA]])>3,1-ABS(Table1[[#This Row],[DEL]]-Table1[[#This Row],[ETA]])/3)} -> 0 | BF8: =IFERROR(IF(Table1[[#This Row],[E2E Total LT]]>0,1-ABS(Table1[[#This Row],[E2E Total LT]]-Table1[[#This Row],[No of Days Total Comm LT (as per contract)]])/Table1[[#This Row],[No of Days Total Comm LT (as per contract)]],0),"") -> 0 | BG8: {=_xlfn.IFS(Table1[[#This Row],[DEL]]="",0,Table1[[#This Row],[STATUS]]="Cancelled",0,Table1[[#This Row],[ORG COUNTRY]]="",0,ISNONTEXT(Table1[[#This Row],[DEL]]),SUM(VLOOKUP(Table1[[#This Row],[Supplier ]],SupplierLeadTimeMaster!$A$2:$B$235,2,FALSE),VLOOKUP(Table1[[#This Row],[ORG COUNTRY]],CountryTransitTimeMaster!$B$2:$C$44,2,FALSE),7,3,5))} -> 0 | BH8: =IFERROR(IF(SUM(Table1[[#This Row],[No of Days Order Placement LT]],Table1[[#This Row],[No of Days Supplier Production Lead Time]],Table1[[#This Row],[No of Days Custom Clearance LT]],Table1[[#This Row],[No of Days ISS Cont Booking LT]],Table1[[#This Row],[No of Days Transit LT]])>500,0,SUM(Table1[[#This Row],[No of Days Order Placement LT]],Table1[[#This Row],[No of Days Supplier Production Lead Time]],Table1[[#This Row],[No of Days Custom Clearance LT]],Table1[[#This Row],[No of Days ISS Cont Booking LT]],Table1[[#This Row],[No of Days Transit LT]])),0) -> 0 | BI8: {=IFERROR(_xlfn.IFS((Table1[[#This Row],[No of Days Supplier Production Lead Time]])=" "," ",Table1[[#This Row],[Actual Lead (PO to Date)]]-Table1[[#This Row],[No of Days Total Comm LT (as per contract)]]<=15,"Healthy",Table1[[#This Row],[Actual Lead (PO to Date)]]-Table1[[#This Row],[No of Days Total Comm LT (as per contract)]]<=30,"Minor",Table1[[#This Row],[Actual Lead (PO to Date)]]-Table1[[#This Row],[No of Days Total Comm LT (as per contract)]]<=45,"Moderate",Table1[[#This Row],[Actual Lead (PO to Date)]]-Table1[[#This Row],[No of Days Total Comm LT (as per contract)]]<=60,"Major",Table1[[#This Row],[Actual Lead (PO to Date)]]-Table1[[#This Row],[No of Days Total Comm LT (as per contract)]]>60,"Severe",ISBLANK(Table1[[#This Row],[DEL]])," ",ISBLANK(Table1[[#This Row],[ETA]])," ",ISBLANK(Table1[[#This Row],[ETD]])," ",ISBLANK(Table1[[#This Row],[PR APPR DATE]])," ",ISBLANK(Table1[[#This Row],[Actual Lead (PO to Date)]])," ",ISBLANK(Table1[[#This Row],[No of Days Total Comm LT (as per contract)]])," ")," ")} -> Healthy | BJ8: {=IFERROR(_xlfn.IFS(Table1[[#This Row],[HEALTH CHECK]]=" ","",Table1[[#This Row],[HEALTH CHECK]]="Healthy"," ",Table1[[#This Row],[ON TIME ORDER PLACEMENT PERF %]]<100%,"PR to PO Delay",Table1[[#This Row],[Supplier committed product readiness performance % ]]<100%,"Product Readiness Delay",Table1[[#This Row],[ISS container booking performance %]]<100%,"Booking Delay",Table1[[#This Row],[ISS Transit Lead Time Perf %]]<100%,"Trans Shipment Delay",Table1[[#This Row],[ISS custom clearance Perf % ]]<100%,"Custom Clearance Delay")," ")} | BK8: {=_xlfn.IFS(ISBLANK(Table1[[#This Row],[PR APPR DATE]]),0,ISBLANK(Table1[[#This Row],[PO APPR DATE]]),0,ISNONTEXT(Table1[[#This Row],[PO APPR DATE]]),Table1[[#This Row],[PO APPR DATE]]-Table1[[#This Row],[PR APPR DATE]])} -> 0 | BL8: {=_xlfn.IFS((Table1[[#This Row],[DEL]])="",0,ISBLANK(Table1[[#This Row],[CRD]]),0,ISBLANK(Table1[[#This Row],[PO APPR DATE]]),0,ISNONTEXT(Table1[[#This Row],[PO APPR DATE]]),Table1[[#This Row],[CRD]]-Table1[[#This Row],[PO APPR DATE]])} -> 0 | BM8: =IFERROR(IF(Table1[[#This Row],[DEL]]>0,Table1[[#This Row],[DEL]]-Table1[[#This Row],[ETA]],0),0) -> 0 | BN8: =IFERROR(IF(Table1[[#This Row],[ETD]]>0,(Table1[[#This Row],[ETD]]-Table1[[#This Row],[CRD]]),0),"") -> 0 | BO8: =IFERROR(IF(Table1[[#This Row],[ETA]]>0,(Table1[[#This Row],[ETA]]-Table1[[#This Row],[ETD]]),0),0) -> 0 | BP8: {=_xlfn.IFS(Table1[[#This Row],[DEL]]="",0,Table1[[#This Row],[DEL]]="",0,ISBLANK(Table1[[#This Row],[PR APPR DATE]]),0,ISBLANK(Table1[[#This Row],[DEL]]),0,ISNONTEXT(Table1[[#This Row],[PR APPR DATE]]),Table1[[#This Row],[DEL]]-Table1[[#This Row],[PR APPR DATE]],Table1[[#This Row],[DEL]]="",0)} -> 0 | BQ8: =Table1[[#This Row],[ORG CHGS (AED)]]/3.673 -> 0 | BR8: =Table1[[#This Row],[FRT CHGS (AED)]]/3.673 -> 0 | BS8: =Table1[[#This Row],[DEST CHGS (AED)]]/3.673 -> 0 | BY8: =SUM(Table1[[#This Row],[ORG CHGS (AED)]],Table1[[#This Row],[FRT CHGS (AED)]],Table1[[#This Row],[DEST CHGS (AED)]]) -> 0 | BZ8: =SUM(Table1[[#This Row],[P2P VALUE]]+Table1[[#This Row],[Ancillary Charges (AED)]]) -> 0 | CD8: =IF(ISBLANK(Table1[[#This Row],[PR DATE]]),"Pending","Logged") -> Pending | CF8: =IF(ISBLANK(Table1[[#This Row],[SPO '#]]),"Pending","Received") -> Pending | CJ8: {=_xlfn.IFS(ISTEXT(Table1[[#This Row],[Invoice '#]]),"Billed",Table1[[#This Row],[PO STATUS]]="Received","Pending",Table1[[#This Row],[PO STATUS]]="Pending","Pending")} -> Pending | CM8: =IF(ISBLANK(Table1[[#This Row],[GRN]]),"Pending","Complete") -> Pending | CU8: =IF(Table1[[#This Row],[DEL]]="","",Table1[[#This Row],[REVISED ETD]]-Table1[[#This Row],[ETD]]) | CV8: =IF(Table1[[#This Row],[DEL]]="","",Table1[[#This Row],[REVISED ETA]]-Table1[[#This Row],[ETA]]) | CW8: =IF(Table1[[#This Row],[DEL]]="","",Table1[[#This Row],[ETA]]-Table1[[#This Row],[PO NEED BY DATE]]) | CX8: =Table1[[#This Row],[Invoice (AED)]]/3.673 -> 0 | CY8: {=_xlfn.IFS(Table1[[#This Row],[STATUS]]="Cancelled",,Table1[[#This Row],[STATUS]]="Pending",,Table1[[#This Row],[STATUS]]="Not Due",,ISNONTEXT(Table1[[#This Row],[CRD]]),Table1[[#This Row],[CRD]]-Table1[[#This Row],[PO NEED BY DATE]])} -> -46021 | CZ8: =IF(Table1[[#This Row],[CRD]]<>"", Table1[[#This Row],[CRD]]-Table1[[#This Row],[PO CREATION DATE]], 0) -> 0 | DA8: =IF(Table1[[#This Row],[REVISED ETD]]<>"", Table1[[#This Row],[REVISED ETD]]-Table1[[#This Row],[CRD]], Table1[[#This Row],[ETD]]-Table1[[#This Row],[CRD]]) -> 0 | DB8: =IF(AND(Table1[[#This Row],[REVISED ETD]]<>"", Table1[[#This Row],[REVISED ETA]]<>""), Table1[[#This Row],[REVISED ETA]]-Table1[[#This Row],[REVISED ETD]], IF(AND(Table1[[#This Row],[REVISED ETA]]<>"", Table1[[#This Row],[REVISED ETD]]=""), Table1[[#This Row],[REVISED ETA]]-Table1[[#This Row],[ETD]], IF(AND(Table1[[#This Row],[REVISED ETA]]="", Table1[[#This Row],[REVISED ETD]]<>""), Table1[[#This Row],[ETA]]-Table1[[#This Row],[REVISED ETD]], IF(AND(Table1[[#This Row],[REVISED ETA]]="", Table1[[#This Row],[REVISED ETD]]=""), Table1[[#This Row],[ETA]]-Table1[[#This Row],[ETD]], "") ) ) ) -> 0 | DC8: =IF(Table1[[#This Row],[REVISED ETA]]<>"", Table1[[#This Row],[DEL]]-Table1[[#This Row],[REVISED ETA]], Table1[[#This Row],[DEL]]-Table1[[#This Row],[ETA]]) -> 0 | DD8: {=_xlfn.IFS(Table1[[#This Row],[STATUS]]="Cancelled",,Table1[[#This Row],[STATUS]]="Pending",,Table1[[#This Row],[STATUS]]="Not Due",,ISNONTEXT(Table1[[#This Row],[ETD]]),Table1[[#This Row],[ETA]]-Table1[[#This Row],[PO NEED BY DATE]])} -> -46021 | DE8: =Table1[[#This Row],[PO NEED BY DATE]]-Table1[[#This Row],[DEL]] -> 46021 | DF8: =SUM(Table1[[#This Row],[CRD TO ETD]],Table1[[#This Row],[ETD TO ETA]],Table1[[#This Row],[ETA TO DEL]],Table1[[#This Row],[NBD TO ETA]],Table1[[#This Row],[NBD TO DEL]]) -> 0
B9: EMIRATES AIRLINE - DEPARTMENT - INFLIGHT SERVICES – 63014 | C9: AL SALEM TRADING ENTERPRISES L.L.C. | D9: 423000433-561 | E9: 422016887-19,422007642-17 | F9: Bags with cutlery|cotton|PO should be fulfilled | G9: PLASTIC BAG FOR BULK CUTLERY (PLASTIC ZIP) |FC Cotton Coaster|STEAM SPOUT | H9: EM000115 | I9: sea_inbound | J9: ISS | K9: FCA | L9: SHPDXBSI25000180 | M9: HBL78464533 | N9: MBL3456723 | O9: CNTX89746352,CETU4522311,UTX9874635 | P9: CNSGH | Q9: SHANGHAI | R9: CHINA | S9: ASIA | T9: AEJEA | U9: 1x20 ft Dry Bulk + 1x20 ft Standard Dry + 1x40 ft Standard Dry | V9: 2 | W9: 1 | X9: 3 | Y9: 4 | Z9: HAPAG-LLOYD | AA9: 45945 | AB9: 45945 | AC9: 45945 | AD9: 45947 | AE9: 45948 | AF9: 45978 | AG9: 45980 | AH9: 45980 | AI9: 45982 | AK9: 46000 | AN9: 46009 | AO9: In Transit | AP9: FW JEBEL ALI | AQ9: 422007642-17-500|422016887-19-1200|423000433-561-400 | AR9: 78.79 | AS9: 886.11 | AT9: 78.79 | AU9: 80 | AV9: Package | AW9: 34500 | AX9: 20.02.25: MAIL SENT TO SUPPLIER SCL JULEE & CARYL COPIED 09.03.25:MAIL SENT TO SUPPLIER SCL JULEE & CARYL COPIED 21.03.25: booking request received r/o sent to agent await relase | IFSIMPGC202676 | 423005557-297-198,000 | 423005557-298- 264,000 05.05.25: 423005557-297-198,000 | 423005557-298-264,000 | GLLCN0010473 06.05.25: shipment connection via SIN will be rolled over due to space issues with vessel, SCL team notified revised ETA 13.05.25: ETA 10-JUN | AY9: Yes | AZ9: No | BA9: =IF(Table1[[#This Row],[PO APPR DATE]]>0,IF(Table1[[#This Row],[PO APPR DATE]]-Table1[[#This Row],[PR APPR DATE]]<=5,1,1-ABS(Table1[[#This Row],[PO APPR DATE]]-Table1[[#This Row],[PR APPR DATE]])/5),0) -> 1 | BB9: {=IFERROR(_xlfn.IFS(ISBLANK(Table1[[#This Row],[PO APPR DATE]]),0,Table1[[#This Row],[CRD]]="",0,Table1[[#This Row],[CRD]]-Table1[[#This Row],[PO APPR DATE]]<=VLOOKUP(Table1[[#This Row],[Supplier ]],SupplierLeadTimeMaster!$A$2:$B$235,2,0),1,(Table1[[#This Row],[CRD]]-Table1[[#This Row],[PO APPR DATE]])>VLOOKUP(Table1[[#This Row],[Supplier ]],SupplierLeadTimeMaster!$A$2:$B$235,2,0),1-ABS(Table1[[#This Row],[CRD]]-Table1[[#This Row],[PO APPR DATE]])/VLOOKUP(Table1[[#This Row],[Supplier ]],SupplierLeadTimeMaster!$A$2:$B$235,2,0)),"")} -> 1 | BC9: =IFERROR(IF(AND(Table1[[#This Row],[ETD]]>0,Table1[[#This Row],[No of Days ISS Cont Booking LT]]>0),IF((Table1[[#This Row],[ETD]]-Table1[[#This Row],[CRD]])<=7,1,1-ABS(Table1[[#This Row],[ETD]]-Table1[[#This Row],[CRD]])/7),0),"") -> 1 | BD9: {=_xlfn.IFS(Table1[[#This Row],[DEL]]="",0,Table1[[#This Row],[ORG COUNTRY]]="",0,ISBLANK(Table1[[#This Row],[ETD]]),0,Table1[[#This Row],[ETA]]="",0,Table1[[#This Row],[ETA]]-Table1[[#This Row],[ETD]]<=VLOOKUP(Table1[[#This Row],[ORG COUNTRY]],CountryTransitTimeMaster!$B$2:$C$44,2,FALSE),1,Table1[[#This Row],[ETA]]-Table1[[#This Row],[ETD]]>VLOOKUP(Table1[[#This Row],[ORG COUNTRY]],CountryTransitTimeMaster!$B$2:$C$44,2,FALSE),1-ABS(Table1[[#This Row],[ETA]]-Table1[[#This Row],[ETD]])/VLOOKUP(Table1[[#This Row],[ORG COUNTRY]],CountryTransitTimeMaster!$B$2:$C$44,2,FALSE))} -> 1 | BE9: {=_xlfn.IFS(Table1[[#This Row],[DEL]]="",0,ISBLANK(Table1[[#This Row],[DEL]]),0,Table1[[#This Row],[DEL]]-Table1[[#This Row],[ETA]]<=3,1,(Table1[[#This Row],[DEL]]-Table1[[#This Row],[ETA]])>3,1-ABS(Table1[[#This Row],[DEL]]-Table1[[#This Row],[ETA]])/3)} -> -2 | BF9: =IFERROR(IF(Table1[[#This Row],[E2E Total LT]]>0,1-ABS(Table1[[#This Row],[E2E Total LT]]-Table1[[#This Row],[No of Days Total Comm LT (as per contract)]])/Table1[[#This Row],[No of Days Total Comm LT (as per contract)]],0),"") -> 0.59428571 | BG9: {=_xlfn.IFS(Table1[[#This Row],[DEL]]="",0,Table1[[#This Row],[STATUS]]="Cancelled",0,Table1[[#This Row],[ORG COUNTRY]]="",0,ISNONTEXT(Table1[[#This Row],[DEL]]),SUM(VLOOKUP(Table1[[#This Row],[Supplier ]],SupplierLeadTimeMaster!$A$2:$B$235,2,FALSE),VLOOKUP(Table1[[#This Row],[ORG COUNTRY]],CountryTransitTimeMaster!$B$2:$C$44,2,FALSE),7,3,5))} -> 107.69231 | BH9: =IFERROR(IF(SUM(Table1[[#This Row],[No of Days Order Placement LT]],Table1[[#This Row],[No of Days Supplier Production Lead Time]],Table1[[#This Row],[No of Days Custom Clearance LT]],Table1[[#This Row],[No of Days ISS Cont Booking LT]],Table1[[#This Row],[No of Days Transit LT]])>500,0,SUM(Table1[[#This Row],[No of Days Order Placement LT]],Table1[[#This Row],[No of Days Supplier Production Lead Time]],Table1[[#This Row],[No of Days Custom Clearance LT]],Table1[[#This Row],[No of Days ISS Cont Booking LT]],Table1[[#This Row],[No of Days Transit LT]])),0) -> 64 | BI9: {=IFERROR(_xlfn.IFS((Table1[[#This Row],[No of Days Supplier Production Lead Time]])=" "," ",Table1[[#This Row],[Actual Lead (PO to Date)]]-Table1[[#This Row],[No of Days Total Comm LT (as per contract)]]<=15,"Healthy",Table1[[#This Row],[Actual Lead (PO to Date)]]-Table1[[#This Row],[No of Days Total Comm LT (as per contract)]]<=30,"Minor",Table1[[#This Row],[Actual Lead (PO to Date)]]-Table1[[#This Row],[No of Days Total Comm LT (as per contract)]]<=45,"Moderate",Table1[[#This Row],[Actual Lead (PO to Date)]]-Table1[[#This Row],[No of Days Total Comm LT (as per contract)]]<=60,"Major",Table1[[#This Row],[Actual Lead (PO to Date)]]-Table1[[#This Row],[No of Days Total Comm LT (as per contract)]]>60,"Severe",ISBLANK(Table1[[#This Row],[DEL]])," ",ISBLANK(Table1[[#This Row],[ETA]])," ",ISBLANK(Table1[[#This Row],[ETD]])," ",ISBLANK(Table1[[#This Row],[PR APPR DATE]])," ",ISBLANK(Table1[[#This Row],[Actual Lead (PO to Date)]])," ",ISBLANK(Table1[[#This Row],[No of Days Total Comm LT (as per contract)]])," ")," ")} -> Healthy | BJ9: {=IFERROR(_xlfn.IFS(Table1[[#This Row],[HEALTH CHECK]]=" ","",Table1[[#This Row],[HEALTH CHECK]]="Healthy"," ",Table1[[#This Row],[ON TIME ORDER PLACEMENT PERF %]]<100%,"PR to PO Delay",Table1[[#This Row],[Supplier committed product readiness performance % ]]<100%,"Product Readiness Delay",Table1[[#This Row],[ISS container booking performance %]]<100%,"Booking Delay",Table1[[#This Row],[ISS Transit Lead Time Perf %]]<100%,"Trans Shipment Delay",Table1[[#This Row],[ISS custom clearance Perf % ]]<100%,"Custom Clearance Delay")," ")} | BK9: {=_xlfn.IFS(ISBLANK(Table1[[#This Row],[PR APPR DATE]]),0,ISBLANK(Table1[[#This Row],[PO APPR DATE]]),0,ISNONTEXT(Table1[[#This Row],[PO APPR DATE]]),Table1[[#This Row],[PO APPR DATE]]-Table1[[#This Row],[PR APPR DATE]])} -> 0 | BL9: {=_xlfn.IFS((Table1[[#This Row],[DEL]])="",0,ISBLANK(Table1[[#This Row],[CRD]]),0,ISBLANK(Table1[[#This Row],[PO APPR DATE]]),0,ISNONTEXT(Table1[[#This Row],[PO APPR DATE]]),Table1[[#This Row],[CRD]]-Table1[[#This Row],[PO APPR DATE]])} -> 33 | BM9: =IFERROR(IF(Table1[[#This Row],[DEL]]>0,Table1[[#This Row],[DEL]]-Table1[[#This Row],[ETA]],0),0) -> 9 | BN9: =IFERROR(IF(Table1[[#This Row],[ETD]]>0,(Table1[[#This Row],[ETD]]-Table1[[#This Row],[CRD]]),0),"") -> 4 | BO9: =IFERROR(IF(Table1[[#This Row],[ETA]]>0,(Table1[[#This Row],[ETA]]-Table1[[#This Row],[ETD]]),0),0) -> 18 | BP9: {=_xlfn.IFS(Table1[[#This Row],[DEL]]="",0,Table1[[#This Row],[DEL]]="",0,ISBLANK(Table1[[#This Row],[PR APPR DATE]]),0,ISBLANK(Table1[[#This Row],[DEL]]),0,ISNONTEXT(Table1[[#This Row],[PR APPR DATE]]),Table1[[#This Row],[DEL]]-Table1[[#This Row],[PR APPR DATE]],Table1[[#This Row],[DEL]]="",0)} -> 64 | BQ9: =Table1[[#This Row],[ORG CHGS (AED)]]/3.673 -> 0 | BR9: =Table1[[#This Row],[FRT CHGS (AED)]]/3.673 -> 0 | BS9: =Table1[[#This Row],[DEST CHGS (AED)]]/3.673 -> 0 | BY9: =SUM(Table1[[#This Row],[ORG CHGS (AED)]],Table1[[#This Row],[FRT CHGS (AED)]],Table1[[#This Row],[DEST CHGS (AED)]]) -> 0 | BZ9: =SUM(Table1[[#This Row],[P2P VALUE]]+Table1[[#This Row],[Ancillary Charges (AED)]]) -> 0 | CA9: shipment billed to customer on one month delay | CB9: 997766554 | CC9: 45983 | CD9: =IF(ISBLANK(Table1[[#This Row],[PR DATE]]),"Pending","Logged") -> Logged | CE9: 786354426281 | CF9: =IF(ISBLANK(Table1[[#This Row],[SPO '#]]),"Pending","Received") -> Received | CJ9: {=_xlfn.IFS(ISTEXT(Table1[[#This Row],[Invoice '#]]),"Billed",Table1[[#This Row],[PO STATUS]]="Received","Pending",Table1[[#This Row],[PO STATUS]]="Pending","Pending")} -> Pending | CL9: 777299992002 | CM9: =IF(ISBLANK(Table1[[#This Row],[GRN]]),"Pending","Complete") -> Complete | CO9: PO874390022 | CR9: PO6652423151 | CU9: =IF(Table1[[#This Row],[DEL]]="","",Table1[[#This Row],[REVISED ETD]]-Table1[[#This Row],[ETD]]) -> -45982 | CV9: =IF(Table1[[#This Row],[DEL]]="","",Table1[[#This Row],[REVISED ETA]]-Table1[[#This Row],[ETA]]) -> -46000 | CW9: =IF(Table1[[#This Row],[DEL]]="","",Table1[[#This Row],[ETA]]-Table1[[#This Row],[PO NEED BY DATE]]) -> 52 | CX9: =Table1[[#This Row],[Invoice (AED)]]/3.673 -> 9392.8669 | CY9: {=_xlfn.IFS(Table1[[#This Row],[STATUS]]="Cancelled",,Table1[[#This Row],[STATUS]]="Pending",,Table1[[#This Row],[STATUS]]="Not Due",,ISNONTEXT(Table1[[#This Row],[CRD]]),Table1[[#This Row],[CRD]]-Table1[[#This Row],[PO NEED BY DATE]])} -> 30 | CZ9: =IF(Table1[[#This Row],[CRD]]<>"", Table1[[#This Row],[CRD]]-Table1[[#This Row],[PO CREATION DATE]], 0) -> 33 | DA9: =IF(Table1[[#This Row],[REVISED ETD]]<>"", Table1[[#This Row],[REVISED ETD]]-Table1[[#This Row],[CRD]], Table1[[#This Row],[ETD]]-Table1[[#This Row],[CRD]]) -> 4 | DB9: =IF(AND(Table1[[#This Row],[REVISED ETD]]<>"", Table1[[#This Row],[REVISED ETA]]<>""), Table1[[#This Row],[REVISED ETA]]-Table1[[#This Row],[REVISED ETD]], IF(AND(Table1[[#This Row],[REVISED ETA]]<>"", Table1[[#This Row],[REVISED ETD]]=""), Table1[[#This Row],[REVISED ETA]]-Table1[[#This Row],[ETD]], IF(AND(Table1[[#This Row],[REVISED ETA]]="", Table1[[#This Row],[REVISED ETD]]<>""), Table1[[#This Row],[ETA]]-Table1[[#This Row],[REVISED ETD]], IF(AND(Table1[[#This Row],[REVISED ETA]]="", Table1[[#This Row],[REVISED ETD]]=""), Table1[[#This Row],[ETA]]-Table1[[#This Row],[ETD]], "") ) ) ) -> 18 | DC9: =IF(Table1[[#This Row],[REVISED ETA]]<>"", Table1[[#This Row],[DEL]]-Table1[[#This Row],[REVISED ETA]], Table1[[#This Row],[DEL]]-Table1[[#This Row],[ETA]]) -> 9 | DD9: {=_xlfn.IFS(Table1[[#This Row],[STATUS]]="Cancelled",,Table1[[#This Row],[STATUS]]="Pending",,Table1[[#This Row],[STATUS]]="Not Due",,ISNONTEXT(Table1[[#This Row],[ETD]]),Table1[[#This Row],[ETA]]-Table1[[#This Row],[PO NEED BY DATE]])} -> 52 | DE9: =Table1[[#This Row],[PO NEED BY DATE]]-Table1[[#This Row],[DEL]] -> -61 | DF9: =SUM(Table1[[#This Row],[CRD TO ETD]],Table1[[#This Row],[ETD TO ETA]],Table1[[#This Row],[ETA TO DEL]],Table1[[#This Row],[NBD TO ETA]],Table1[[#This Row],[NBD TO DEL]]) -> 22 | DH9: SE5673422
B10: EMIRATES AIRLINE-RETAIL-CCC: 63032 | C10: AL SALEM TRADING ENTERPRISES L.L.C. | D10: 423000433-562 | E10: 423000433-561 | F10: Bags with cutlery|cutlery | G10: PLASTIC BAG FOR BULK CUTLERY (PLASTIC ZIP) | H10: EM000127 | I10: sea_inbound | J10: Direct | K10: EXW | P10: CNSZX | Q10: SHENZHEN BAOAN | R10: CHINA | S10: ASIA | T10: AEDXB | U10: 1x20 ft Standard Dry + 2x40 ft Standard Dry + 2x40 ft High Cube | V10: 1 | W10: 2 | X10: 5 | Y10: 5 | AA10: 45945 | AB10: 45945 | AC10: 45945 | AD10: 45947 | AE10: 45947 | AI10: 46002 | AK10: 46004 | AO10: On Going | AP10: FW RAMOUL | AQ10: 423000433-561-43600|423000433-562-3000 | AR10: 23.66 | AS10: 3422.45 | AT10: 23.66 | AU10: 70 | AV10: Package | BA10: =IF(Table1[[#This Row],[PO APPR DATE]]>0,IF(Table1[[#This Row],[PO APPR DATE]]-Table1[[#This Row],[PR APPR DATE]]<=5,1,1-ABS(Table1[[#This Row],[PO APPR DATE]]-Table1[[#This Row],[PR APPR DATE]])/5),0) -> 1 | BB10: {=IFERROR(_xlfn.IFS(ISBLANK(Table1[[#This Row],[PO APPR DATE]]),0,Table1[[#This Row],[CRD]]="",0,Table1[[#This Row],[CRD]]-Table1[[#This Row],[PO APPR DATE]]<=VLOOKUP(Table1[[#This Row],[Supplier ]],SupplierLeadTimeMaster!$A$2:$B$235,2,0),1,(Table1[[#This Row],[CRD]]-Table1[[#This Row],[PO APPR DATE]])>VLOOKUP(Table1[[#This Row],[Supplier ]],SupplierLeadTimeMaster!$A$2:$B$235,2,0),1-ABS(Table1[[#This Row],[CRD]]-Table1[[#This Row],[PO APPR DATE]])/VLOOKUP(Table1[[#This Row],[Supplier ]],SupplierLeadTimeMaster!$A$2:$B$235,2,0)),"")} -> 0 | BC10: =IFERROR(IF(AND(Table1[[#This Row],[ETD]]>0,Table1[[#This Row],[No of Days ISS Cont Booking LT]]>0),IF((Table1[[#This Row],[ETD]]-Table1[[#This Row],[CRD]])<=7,1,1-ABS(Table1[[#This Row],[ETD]]-Table1[[#This Row],[CRD]])/7),0),"") -> -6570.7143 | BD10: {=_xlfn.IFS(Table1[[#This Row],[DEL]]="",0,Table1[[#This Row],[ORG COUNTRY]]="",0,ISBLANK(Table1[[#This Row],[ETD]]),0,Table1[[#This Row],[ETA]]="",0,Table1[[#This Row],[ETA]]-Table1[[#This Row],[ETD]]<=VLOOKUP(Table1[[#This Row],[ORG COUNTRY]],CountryTransitTimeMaster!$B$2:$C$44,2,FALSE),1,Table1[[#This Row],[ETA]]-Table1[[#This Row],[ETD]]>VLOOKUP(Table1[[#This Row],[ORG COUNTRY]],CountryTransitTimeMaster!$B$2:$C$44,2,FALSE),1-ABS(Table1[[#This Row],[ETA]]-Table1[[#This Row],[ETD]])/VLOOKUP(Table1[[#This Row],[ORG COUNTRY]],CountryTransitTimeMaster!$B$2:$C$44,2,FALSE))} -> 0 | BE10: {=_xlfn.IFS(Table1[[#This Row],[DEL]]="",0,ISBLANK(Table1[[#This Row],[DEL]]),0,Table1[[#This Row],[DEL]]-Table1[[#This Row],[ETA]]<=3,1,(Table1[[#This Row],[DEL]]-Table1[[#This Row],[ETA]])>3,1-ABS(Table1[[#This Row],[DEL]]-Table1[[#This Row],[ETA]])/3)} -> 0 | BF10: =IFERROR(IF(Table1[[#This Row],[E2E Total LT]]>0,1-ABS(Table1[[#This Row],[E2E Total LT]]-Table1[[#This Row],[No of Days Total Comm LT (as per contract)]])/Table1[[#This Row],[No of Days Total Comm LT (as per contract)]],0),"") -> 0 | BG10: {=_xlfn.IFS(Table1[[#This Row],[DEL]]="",0,Table1[[#This Row],[STATUS]]="Cancelled",0,Table1[[#This Row],[ORG COUNTRY]]="",0,ISNONTEXT(Table1[[#This Row],[DEL]]),SUM(VLOOKUP(Table1[[#This Row],[Supplier ]],SupplierLeadTimeMaster!$A$2:$B$235,2,FALSE),VLOOKUP(Table1[[#This Row],[ORG COUNTRY]],CountryTransitTimeMaster!$B$2:$C$44,2,FALSE),7,3,5))} -> 0 | BH10: =IFERROR(IF(SUM(Table1[[#This Row],[No of Days Order Placement LT]],Table1[[#This Row],[No of Days Supplier Production Lead Time]],Table1[[#This Row],[No of Days Custom Clearance LT]],Table1[[#This Row],[No of Days ISS Cont Booking LT]],Table1[[#This Row],[No of Days Transit LT]])>500,0,SUM(Table1[[#This Row],[No of Days Order Placement LT]],Table1[[#This Row],[No of Days Supplier Production Lead Time]],Table1[[#This Row],[No of Days Custom Clearance LT]],Table1[[#This Row],[No of Days ISS Cont Booking LT]],Table1[[#This Row],[No of Days Transit LT]])),0) -> 0 | BI10: {=IFERROR(_xlfn.IFS((Table1[[#This Row],[No of Days Supplier Production Lead Time]])=" "," ",Table1[[#This Row],[Actual Lead (PO to Date)]]-Table1[[#This Row],[No of Days Total Comm LT (as per contract)]]<=15,"Healthy",Table1[[#This Row],[Actual Lead (PO to Date)]]-Table1[[#This Row],[No of Days Total Comm LT (as per contract)]]<=30,"Minor",Table1[[#This Row],[Actual Lead (PO to Date)]]-Table1[[#This Row],[No of Days Total Comm LT (as per contract)]]<=45,"Moderate",Table1[[#This Row],[Actual Lead (PO to Date)]]-Table1[[#This Row],[No of Days Total Comm LT (as per contract)]]<=60,"Major",Table1[[#This Row],[Actual Lead (PO to Date)]]-Table1[[#This Row],[No of Days Total Comm LT (as per contract)]]>60,"Severe",ISBLANK(Table1[[#This Row],[DEL]])," ",ISBLANK(Table1[[#This Row],[ETA]])," ",ISBLANK(Table1[[#This Row],[ETD]])," ",ISBLANK(Table1[[#This Row],[PR APPR DATE]])," ",ISBLANK(Table1[[#This Row],[Actual Lead (PO to Date)]])," ",ISBLANK(Table1[[#This Row],[No of Days Total Comm LT (as per contract)]])," ")," ")} -> Healthy | BJ10: {=IFERROR(_xlfn.IFS(Table1[[#This Row],[HEALTH CHECK]]=" ","",Table1[[#This Row],[HEALTH CHECK]]="Healthy"," ",Table1[[#This Row],[ON TIME ORDER PLACEMENT PERF %]]<100%,"PR to PO Delay",Table1[[#This Row],[Supplier committed product readiness performance % ]]<100%,"Product Readiness Delay",Table1[[#This Row],[ISS container booking performance %]]<100%,"Booking Delay",Table1[[#This Row],[ISS Transit Lead Time Perf %]]<100%,"Trans Shipment Delay",Table1[[#This Row],[ISS custom clearance Perf % ]]<100%,"Custom Clearance Delay")," ")} | BK10: {=_xlfn.IFS(ISBLANK(Table1[[#This Row],[PR APPR DATE]]),0,ISBLANK(Table1[[#This Row],[PO APPR DATE]]),0,ISNONTEXT(Table1[[#This Row],[PO APPR DATE]]),Table1[[#This Row],[PO APPR DATE]]-Table1[[#This Row],[PR APPR DATE]])} -> 0 | BL10: {=_xlfn.IFS((Table1[[#This Row],[DEL]])="",0,ISBLANK(Table1[[#This Row],[CRD]]),0,ISBLANK(Table1[[#This Row],[PO APPR DATE]]),0,ISNONTEXT(Table1[[#This Row],[PO APPR DATE]]),Table1[[#This Row],[CRD]]-Table1[[#This Row],[PO APPR DATE]])} -> 0 | BM10: =IFERROR(IF(Table1[[#This Row],[DEL]]>0,Table1[[#This Row],[DEL]]-Table1[[#This Row],[ETA]],0),0) -> 0 | BN10: =IFERROR(IF(Table1[[#This Row],[ETD]]>0,(Table1[[#This Row],[ETD]]-Table1[[#This Row],[CRD]]),0),"") -> 46002 | BO10: =IFERROR(IF(Table1[[#This Row],[ETA]]>0,(Table1[[#This Row],[ETA]]-Table1[[#This Row],[ETD]]),0),0) -> 2 | BP10: {=_xlfn.IFS(Table1[[#This Row],[DEL]]="",0,Table1[[#This Row],[DEL]]="",0,ISBLANK(Table1[[#This Row],[PR APPR DATE]]),0,ISBLANK(Table1[[#This Row],[DEL]]),0,ISNONTEXT(Table1[[#This Row],[PR APPR DATE]]),Table1[[#This Row],[DEL]]-Table1[[#This Row],[PR APPR DATE]],Table1[[#This Row],[DEL]]="",0)} -> 0 | BQ10: =Table1[[#This Row],[ORG CHGS (AED)]]/3.673 -> 0 | BR10: =Table1[[#This Row],[FRT CHGS (AED)]]/3.673 -> 0 | BS10: =Table1[[#This Row],[DEST CHGS (AED)]]/3.673 -> 0 | BY10: =SUM(Table1[[#This Row],[ORG CHGS (AED)]],Table1[[#This Row],[FRT CHGS (AED)]],Table1[[#This Row],[DEST CHGS (AED)]]) -> 0 | BZ10: =SUM(Table1[[#This Row],[P2P VALUE]]+Table1[[#This Row],[Ancillary Charges (AED)]]) -> 0 | CD10: =IF(ISBLANK(Table1[[#This Row],[PR DATE]]),"Pending","Logged") -> Pending | CF10: =IF(ISBLANK(Table1[[#This Row],[SPO '#]]),"Pending","Received") -> Pending | CJ10: {=_xlfn.IFS(ISTEXT(Table1[[#This Row],[Invoice '#]]),"Billed",Table1[[#This Row],[PO STATUS]]="Received","Pending",Table1[[#This Row],[PO STATUS]]="Pending","Pending")} -> Pending | CM10: =IF(ISBLANK(Table1[[#This Row],[GRN]]),"Pending","Complete") -> Pending | CU10: =IF(Table1[[#This Row],[DEL]]="","",Table1[[#This Row],[REVISED ETD]]-Table1[[#This Row],[ETD]]) | CV10: =IF(Table1[[#This Row],[DEL]]="","",Table1[[#This Row],[REVISED ETA]]-Table1[[#This Row],[ETA]]) | CW10: =IF(Table1[[#This Row],[DEL]]="","",Table1[[#This Row],[ETA]]-Table1[[#This Row],[PO NEED BY DATE]]) | CX10: =Table1[[#This Row],[Invoice (AED)]]/3.673 -> 0 | CY10: {=_xlfn.IFS(Table1[[#This Row],[STATUS]]="Cancelled",,Table1[[#This Row],[STATUS]]="Pending",,Table1[[#This Row],[STATUS]]="Not Due",,ISNONTEXT(Table1[[#This Row],[CRD]]),Table1[[#This Row],[CRD]]-Table1[[#This Row],[PO NEED BY DATE]])} -> -45947 | CZ10: =IF(Table1[[#This Row],[CRD]]<>"", Table1[[#This Row],[CRD]]-Table1[[#This Row],[PO CREATION DATE]], 0) -> 0 | DA10: =IF(Table1[[#This Row],[REVISED ETD]]<>"", Table1[[#This Row],[REVISED ETD]]-Table1[[#This Row],[CRD]], Table1[[#This Row],[ETD]]-Table1[[#This Row],[CRD]]) -> 46002 | DB10: =IF(AND(Table1[[#This Row],[REVISED ETD]]<>"", Table1[[#This Row],[REVISED ETA]]<>""), Table1[[#This Row],[REVISED ETA]]-Table1[[#This Row],[REVISED ETD]], IF(AND(Table1[[#This Row],[REVISED ETA]]<>"", Table1[[#This Row],[REVISED ETD]]=""), Table1[[#This Row],[REVISED ETA]]-Table1[[#This Row],[ETD]], IF(AND(Table1[[#This Row],[REVISED ETA]]="", Table1[[#This Row],[REVISED ETD]]<>""), Table1[[#This Row],[ETA]]-Table1[[#This Row],[REVISED ETD]], IF(AND(Table1[[#This Row],[REVISED ETA]]="", Table1[[#This Row],[REVISED ETD]]=""), Table1[[#This Row],[ETA]]-Table1[[#This Row],[ETD]], "") ) ) ) -> 2 | DC10: =IF(Table1[[#This Row],[REVISED ETA]]<>"", Table1[[#This Row],[DEL]]-Table1[[#This Row],[REVISED ETA]], Table1[[#This Row],[DEL]]-Table1[[#This Row],[ETA]]) -> -46004 | DD10: {=_xlfn.IFS(Table1[[#This Row],[STATUS]]="Cancelled",,Table1[[#This Row],[STATUS]]="Pending",,Table1[[#This Row],[STATUS]]="Not Due",,ISNONTEXT(Table1[[#This Row],[ETD]]),Table1[[#This Row],[ETA]]-Table1[[#This Row],[PO NEED BY DATE]])} -> 57 | DE10: =Table1[[#This Row],[PO NEED BY DATE]]-Table1[[#This Row],[DEL]] -> 45947 | DF10: =SUM(Table1[[#This Row],[CRD TO ETD]],Table1[[#This Row],[ETD TO ETA]],Table1[[#This Row],[ETA TO DEL]],Table1[[#This Row],[NBD TO ETA]],Table1[[#This Row],[NBD TO DEL]]) -> 46004
C11: AL SALEM TRADING ENTERPRISES L.L.C. | D11: 423000433-561 | F11: Bags with cutlery | G11: PLASTIC BAG FOR BULK CUTLERY (PLASTIC ZIP) | H11: EM000126 | AA11: 45945 | AB11: 45945 | AC11: 45945 | AD11: 45947 | AE11: 45948 | AO11: On Going | AQ11: 10000 | BA11: =IF(Table1[[#This Row],[PO APPR DATE]]>0,IF(Table1[[#This Row],[PO APPR DATE]]-Table1[[#This Row],[PR APPR DATE]]<=5,1,1-ABS(Table1[[#This Row],[PO APPR DATE]]-Table1[[#This Row],[PR APPR DATE]])/5),0) -> 1 | BB11: {=IFERROR(_xlfn.IFS(ISBLANK(Table1[[#This Row],[PO APPR DATE]]),0,Table1[[#This Row],[CRD]]="",0,Table1[[#This Row],[CRD]]-Table1[[#This Row],[PO APPR DATE]]<=VLOOKUP(Table1[[#This Row],[Supplier ]],SupplierLeadTimeMaster!$A$2:$B$235,2,0),1,(Table1[[#This Row],[CRD]]-Table1[[#This Row],[PO APPR DATE]])>VLOOKUP(Table1[[#This Row],[Supplier ]],SupplierLeadTimeMaster!$A$2:$B$235,2,0),1-ABS(Table1[[#This Row],[CRD]]-Table1[[#This Row],[PO APPR DATE]])/VLOOKUP(Table1[[#This Row],[Supplier ]],SupplierLeadTimeMaster!$A$2:$B$235,2,0)),"")} -> 0 | BC11: =IFERROR(IF(AND(Table1[[#This Row],[ETD]]>0,Table1[[#This Row],[No of Days ISS Cont Booking LT]]>0),IF((Table1[[#This Row],[ETD]]-Table1[[#This Row],[CRD]])<=7,1,1-ABS(Table1[[#This Row],[ETD]]-Table1[[#This Row],[CRD]])/7),0),"") -> 0 | BD11: {=_xlfn.IFS(Table1[[#This Row],[DEL]]="",0,Table1[[#This Row],[ORG COUNTRY]]="",0,ISBLANK(Table1[[#This Row],[ETD]]),0,Table1[[#This Row],[ETA]]="",0,Table1[[#This Row],[ETA]]-Table1[[#This Row],[ETD]]<=VLOOKUP(Table1[[#This Row],[ORG COUNTRY]],CountryTransitTimeMaster!$B$2:$C$44,2,FALSE),1,Table1[[#This Row],[ETA]]-Table1[[#This Row],[ETD]]>VLOOKUP(Table1[[#This Row],[ORG COUNTRY]],CountryTransitTimeMaster!$B$2:$C$44,2,FALSE),1-ABS(Table1[[#This Row],[ETA]]-Table1[[#This Row],[ETD]])/VLOOKUP(Table1[[#This Row],[ORG COUNTRY]],CountryTransitTimeMaster!$B$2:$C$44,2,FALSE))} -> 0 | BE11: {=_xlfn.IFS(Table1[[#This Row],[DEL]]="",0,ISBLANK(Table1[[#This Row],[DEL]]),0,Table1[[#This Row],[DEL]]-Table1[[#This Row],[ETA]]<=3,1,(Table1[[#This Row],[DEL]]-Table1[[#This Row],[ETA]])>3,1-ABS(Table1[[#This Row],[DEL]]-Table1[[#This Row],[ETA]])/3)} -> 0 | BF11: =IFERROR(IF(Table1[[#This Row],[E2E Total LT]]>0,1-ABS(Table1[[#This Row],[E2E Total LT]]-Table1[[#This Row],[No of Days Total Comm LT (as per contract)]])/Table1[[#This Row],[No of Days Total Comm LT (as per contract)]],0),"") -> 0 | BG11: {=_xlfn.IFS(Table1[[#This Row],[DEL]]="",0,Table1[[#This Row],[STATUS]]="Cancelled",0,Table1[[#This Row],[ORG COUNTRY]]="",0,ISNONTEXT(Table1[[#This Row],[DEL]]),SUM(VLOOKUP(Table1[[#This Row],[Supplier ]],SupplierLeadTimeMaster!$A$2:$B$235,2,FALSE),VLOOKUP(Table1[[#This Row],[ORG COUNTRY]],CountryTransitTimeMaster!$B$2:$C$44,2,FALSE),7,3,5))} -> 0 | BH11: =IFERROR(IF(SUM(Table1[[#This Row],[No of Days Order Placement LT]],Table1[[#This Row],[No of Days Supplier Production Lead Time]],Table1[[#This Row],[No of Days Custom Clearance LT]],Table1[[#This Row],[No of Days ISS Cont Booking LT]],Table1[[#This Row],[No of Days Transit LT]])>500,0,SUM(Table1[[#This Row],[No of Days Order Placement LT]],Table1[[#This Row],[No of Days Supplier Production Lead Time]],Table1[[#This Row],[No of Days Custom Clearance LT]],Table1[[#This Row],[No of Days ISS Cont Booking LT]],Table1[[#This Row],[No of Days Transit LT]])),0) -> 0 | BI11: {=IFERROR(_xlfn.IFS((Table1[[#This Row],[No of Days Supplier Production Lead Time]])=" "," ",Table1[[#This Row],[Actual Lead (PO to Date)]]-Table1[[#This Row],[No of Days Total Comm LT (as per contract)]]<=15,"Healthy",Table1[[#This Row],[Actual Lead (PO to Date)]]-Table1[[#This Row],[No of Days Total Comm LT (as per contract)]]<=30,"Minor",Table1[[#This Row],[Actual Lead (PO to Date)]]-Table1[[#This Row],[No of Days Total Comm LT (as per contract)]]<=45,"Moderate",Table1[[#This Row],[Actual Lead (PO to Date)]]-Table1[[#This Row],[No of Days Total Comm LT (as per contract)]]<=60,"Major",Table1[[#This Row],[Actual Lead (PO to Date)]]-Table1[[#This Row],[No of Days Total Comm LT (as per contract)]]>60,"Severe",ISBLANK(Table1[[#This Row],[DEL]])," ",ISBLANK(Table1[[#This Row],[ETA]])," ",ISBLANK(Table1[[#This Row],[ETD]])," ",ISBLANK(Table1[[#This Row],[PR APPR DATE]])," ",ISBLANK(Table1[[#This Row],[Actual Lead (PO to Date)]])," ",ISBLANK(Table1[[#This Row],[No of Days Total Comm LT (as per contract)]])," ")," ")} -> Healthy | BJ11: {=IFERROR(_xlfn.IFS(Table1[[#This Row],[HEALTH CHECK]]=" ","",Table1[[#This Row],[HEALTH CHECK]]="Healthy"," ",Table1[[#This Row],[ON TIME ORDER PLACEMENT PERF %]]<100%,"PR to PO Delay",Table1[[#This Row],[Supplier committed product readiness performance % ]]<100%,"Product Readiness Delay",Table1[[#This Row],[ISS container booking performance %]]<100%,"Booking Delay",Table1[[#This Row],[ISS Transit Lead Time Perf %]]<100%,"Trans Shipment Delay",Table1[[#This Row],[ISS custom clearance Perf % ]]<100%,"Custom Clearance Delay")," ")} | BK11: {=_xlfn.IFS(ISBLANK(Table1[[#This Row],[PR APPR DATE]]),0,ISBLANK(Table1[[#This Row],[PO APPR DATE]]),0,ISNONTEXT(Table1[[#This Row],[PO APPR DATE]]),Table1[[#This Row],[PO APPR DATE]]-Table1[[#This Row],[PR APPR DATE]])} -> 0 | BL11: {=_xlfn.IFS((Table1[[#This Row],[DEL]])="",0,ISBLANK(Table1[[#This Row],[CRD]]),0,ISBLANK(Table1[[#This Row],[PO APPR DATE]]),0,ISNONTEXT(Table1[[#This Row],[PO APPR DATE]]),Table1[[#This Row],[CRD]]-Table1[[#This Row],[PO APPR DATE]])} -> 0 | BM11: =IFERROR(IF(Table1[[#This Row],[DEL]]>0,Table1[[#This Row],[DEL]]-Table1[[#This Row],[ETA]],0),0) -> 0 | BN11: =IFERROR(IF(Table1[[#This Row],[ETD]]>0,(Table1[[#This Row],[ETD]]-Table1[[#This Row],[CRD]]),0),"") -> 0 | BO11: =IFERROR(IF(Table1[[#This Row],[ETA]]>0,(Table1[[#This Row],[ETA]]-Table1[[#This Row],[ETD]]),0),0) -> 0 | BP11: {=_xlfn.IFS(Table1[[#This Row],[DEL]]="",0,Table1[[#This Row],[DEL]]="",0,ISBLANK(Table1[[#This Row],[PR APPR DATE]]),0,ISBLANK(Table1[[#This Row],[DEL]]),0,ISNONTEXT(Table1[[#This Row],[PR APPR DATE]]),Table1[[#This Row],[DEL]]-Table1[[#This Row],[PR APPR DATE]],Table1[[#This Row],[DEL]]="",0)} -> 0 | BQ11: =Table1[[#This Row],[ORG CHGS (AED)]]/3.673 -> 0 | BR11: =Table1[[#This Row],[FRT CHGS (AED)]]/3.673 -> 0 | BS11: =Table1[[#This Row],[DEST CHGS (AED)]]/3.673 -> 0 | BY11: =SUM(Table1[[#This Row],[ORG CHGS (AED)]],Table1[[#This Row],[FRT CHGS (AED)]],Table1[[#This Row],[DEST CHGS (AED)]]) -> 0 | BZ11: =SUM(Table1[[#This Row],[P2P VALUE]]+Table1[[#This Row],[Ancillary Charges (AED)]]) -> 0 | CD11: =IF(ISBLANK(Table1[[#This Row],[PR DATE]]),"Pending","Logged") -> Pending | CF11: =IF(ISBLANK(Table1[[#This Row],[SPO '#]]),"Pending","Received") -> Pending | CJ11: {=_xlfn.IFS(ISTEXT(Table1[[#This Row],[Invoice '#]]),"Billed",Table1[[#This Row],[PO STATUS]]="Received","Pending",Table1[[#This Row],[PO STATUS]]="Pending","Pending")} -> Pending | CM11: =IF(ISBLANK(Table1[[#This Row],[GRN]]),"Pending","Complete") -> Pending | CU11: =IF(Table1[[#This Row],[DEL]]="","",Table1[[#This Row],[REVISED ETD]]-Table1[[#This Row],[ETD]]) | CV11: =IF(Table1[[#This Row],[DEL]]="","",Table1[[#This Row],[REVISED ETA]]-Table1[[#This Row],[ETA]]) | CW11: =IF(Table1[[#This Row],[DEL]]="","",Table1[[#This Row],[ETA]]-Table1[[#This Row],[PO NEED BY DATE]]) | CX11: =Table1[[#This Row],[Invoice (AED)]]/3.673 -> 0 | CY11: {=_xlfn.IFS(Table1[[#This Row],[STATUS]]="Cancelled",,Table1[[#This Row],[STATUS]]="Pending",,Table1[[#This Row],[STATUS]]="Not Due",,ISNONTEXT(Table1[[#This Row],[CRD]]),Table1[[#This Row],[CRD]]-Table1[[#This Row],[PO NEED BY DATE]])} -> -45948 | CZ11: =IF(Table1[[#This Row],[CRD]]<>"", Table1[[#This Row],[CRD]]-Table1[[#This Row],[PO CREATION DATE]], 0) -> 0 | DA11: =IF(Table1[[#This Row],[REVISED ETD]]<>"", Table1[[#This Row],[REVISED ETD]]-Table1[[#This Row],[CRD]], Table1[[#This Row],[ETD]]-Table1[[#This Row],[CRD]]) -> 0 | DB11: =IF(AND(Table1[[#This Row],[REVISED ETD]]<>"", Table1[[#This Row],[REVISED ETA]]<>""), Table1[[#This Row],[REVISED ETA]]-Table1[[#This Row],[REVISED ETD]], IF(AND(Table1[[#This Row],[REVISED ETA]]<>"", Table1[[#This Row],[REVISED ETD]]=""), Table1[[#This Row],[REVISED ETA]]-Table1[[#This Row],[ETD]], IF(AND(Table1[[#This Row],[REVISED ETA]]="", Table1[[#This Row],[REVISED ETD]]<>""), Table1[[#This Row],[ETA]]-Table1[[#This Row],[REVISED ETD]], IF(AND(Table1[[#This Row],[REVISED ETA]]="", Table1[[#This Row],[REVISED ETD]]=""), Table1[[#This Row],[ETA]]-Table1[[#This Row],[ETD]], "") ) ) ) -> 0 | DC11: =IF(Table1[[#This Row],[REVISED ETA]]<>"", Table1[[#This Row],[DEL]]-Table1[[#This Row],[REVISED ETA]], Table1[[#This Row],[DEL]]-Table1[[#This Row],[ETA]]) -> 0 | DD11: {=_xlfn.IFS(Table1[[#This Row],[STATUS]]="Cancelled",,Table1[[#This Row],[STATUS]]="Pending",,Table1[[#This Row],[STATUS]]="Not Due",,ISNONTEXT(Table1[[#This Row],[ETD]]),Table1[[#This Row],[ETA]]-Table1[[#This Row],[PO NEED BY DATE]])} -> -45948 | DE11: =Table1[[#This Row],[PO NEED BY DATE]]-Table1[[#This Row],[DEL]] -> 45948 | DF11: =SUM(Table1[[#This Row],[CRD TO ETD]],Table1[[#This Row],[ETD TO ETA]],Table1[[#This Row],[ETA TO DEL]],Table1[[#This Row],[NBD TO ETA]],Table1[[#This Row],[NBD TO DEL]]) -> 0

Sheet ChargeServiceMapping-Origin
A1: Service | B1: Charge | C1: Category | D1: Status
A2: air_outbound | B2: PICK-UP CHARGES | C2: Origin Charge | D2: Active
A3: air_outbound | B3: DOCUMENTATION CHARGE | C3: Origin Charge | D3: Active
A4: air_inbound | B4: HANDLING CHARGES | C4: Origin Charge | D4: Active
A5: air_inbound | B5: CUSTOMS CLEARANCE CHARGES | C5: Origin Charge | D5: Active
A6: air_inbound | B6: DOCUMENTATION CHARGE | C6: Origin Charge | D6: Active
A7: air_inbound | B7: PICK-UP CHARGES | C7: Origin Charge | D7: Active
A8: sea_outbound | B8: FOB CHARGES | C8: Origin Charge | D8: Active

Sheet ChargeServiceMapping-Destinatio
A1: Service | B1: Charge | C1: Category | D1: Status
A2: air_outbound | B2: DESTINATION HANDLING | C2: Destination Charge | D2: Active
A3: air_outbound | B3: DESTINATION HAULAGE CHARGES | C3: Destination Charge | D3: Active
A4: air_outbound | B4: CLEARANCE CHARGES (DEST.) | C4: Destination Charge | D4: Active
A5: air_outbound | B5: DOCUMENTATION FEE - DEST | C5: Destination Charge | D5: Active
A6: air_inbound | B6: HANDLING CHARGES | C6: Destination Charge | D6: Active
A7: air_inbound | B7: DOCUMENTATION CHARGE | C7: Destination Charge | D7: Active
A8: air_inbound | B8: TRANSPORT CHARGES | C8: Destination Charge | D8: Active
A9: sea_outbound | B9: DESTINATION CHARGES | C9: Destination Charge | D9: Active
A10: sea_inbound | B10: DESTINATION CHARGES | C10: Destination Charge | D10: Active

Sheet ChargeServiceMapping-Freight
A1: Service | B1: Charge | C1: Category | D1: Status
A2: sea_outbound | B2: OCEAN FREIGHT | C2: Freight Charge | D2: Active
A3: sea_inbound | B3: OCEAN FREIGHT | C3: Freight Charge | D3: Active

Sheet ChargeServiceMapping-Ancillary
A1: Service | B1: Charge | C1: Category | D1: Status
A2: air_inbound | B2: DCAA CHARGE | C2: Ancillary Charge | D2: Active
A3: air_inbound | B3: SANITARY FEE | C3: Ancillary Charge | D3: Active
A4: air_inbound | B4: FDA PERMIT | C4: Ancillary Charge | D4: Active
A5: air_inbound | B5: HEALTH CERT | C5: Ancillary Charge | D5: Active
A6: air_inbound | B6: MPI CHARGE | C6: Ancillary Charge | D6: Active
A7: air_inbound | B7: QUARANTINE CHARGE | C7: Ancillary Charge | D7: Active
A8: air_inbound | B8: XRAY FEE | C8: Ancillary Charge | D8: Active
A9: air_inbound | B9: LABOUR CHARGE | C9: Ancillary Charge | D9: Active
A10: air_inbound | B10: STORAGE CHARGE | C10: Ancillary Charge | D10: Active
A11: air_inbound | B11: CUSTOMS DUTY | C11: Ancillary Charge | D11: Active
A12: air_inbound | B12: IMPORT VAT CHARGES | C12: Ancillary Charge | D12: Active
... A59: sea_cross_trade | B59: INSPECTION CHARGES | C59: Ancillary Charge | D59: Active

Sheet Sheet1
A1: 46009 | B1: 46000 | C1: =A1-B1 -> 9 | D1: 70 | E1: =1-ABS(C1)/D1 -> 0.87142857 | F1: =1-ABS(A1-B1)/3 -> -2

Sheet SupplierLeadTimeMaster
A1: SHIPPER | B1: Average of LEAD TIME
A2: ABERT SPA | B2: 60
A3: ADA PACIFIC | B3: 65
A4: AEROFOOD ACS DENPASAR | B4: 60
A5: AIRE INFLIGHT | B5: 60
A6: AL SALEM TRADING ENTERPRISES L.L.C. | B6: 60
A7: BIECHER S.A. | B7: 0
A8: BUZZ PRODUCTS PTY LTD | B8: 90
A9: BVLGARI IRELAND | B9: 60
A10: CASTELLO MONTE VIBIANO VECCHIO S.R.L. | B10: 58
A11: CHAPOUTIER | B11: 0
A12: CHATSFORD | B12: 85
A13: COMPAGNIE MEDOCAINE | B13: 0
... A130: E.F.B FZC | B130: 60

Sheet CountryTransitTimeMaster
A1: Code | B1: Country | C1: Average of TRANSIT TIME
A2: AU | B2: AUSTRALIA | C2: 47.5
A3: BE | B3: BELGIUM | C3: 35
A4: CN | B4: CHINA | C4: 32.692308
A5: DK | B5: DENMARK | C5: 45
A6: FR | B6: FRANCE | C6: 25
A7: DE | B7: GERMANY | C7: 45
A8: HK | B8: HONG KONG | C8: 25
A9: IN | B9: INDIA | C9: 19
A10: ID | B10: INDONESIA | C10: 20
A11: IE | B11: IRELAND | C11: 45
A12: IT | B12: ITALY | C12: 38.75
A13: JP | B13: JAPAN | C13: 38.333333
... A43: AE | B43: UNITED ARAB EMIRATES | C43: 1
